{
    "buildCode": "2",
    "data": {
        "30007": {
            "pmDataList": [
                {
                    "counterId": 30007,
                    "counterValue": 50.0,
                    "dnId": 118748818,
                    "dstOffset": 60,
                    "period": 300,
                    "startTime": 1752530400,
                    "timeZoneOffset": 60
                },
                {
                    "counterId": 30007,
                    "counterValue": 50.0,
                    "dnId": 118748818,
                    "dstOffset": 60,
                    "period": 300,
                    "startTime": 1752530700,
                    "timeZoneOffset": 60
                },
                {
                    "counterId": 30007,
                    "counterValue": 49.0,
                    "dnId": 118748818,
                    "dstOffset": 60,
                    "period": 300,
                    "startTime": 1752531000,
                    "timeZoneOffset": 60
                },
                {
                    "counterId": 30007,
                    "counterValue": 49.0,
                    "dnId": 118748818,
                    "dstOffset": 60,
                    "period": 300,
                    "startTime": 1752531300,
                    "timeZoneOffset": 60
                },
                {
                    "counterId": 30007,
                    "counterValue": 49.0,
                    "dnId": 118748818,
                    "dstOffset": 60,
                    "period": 300,
                    "startTime": 1752531600,
                    "timeZoneOffset": 60
                },
                {
                    "counterId": 30007,
                    "counterValue": 48.0,
                    "dnId": 118748818,
                    "dstOffset": 60,
                    "period": 300,
                    "startTime": 1752531900,
                    "timeZoneOffset": 60
                },
                {
                    "counterId": 30007,
                    "counterValue": 48.0,
                    "dnId": 118748818,
                    "dstOffset": 60,
                    "period": 300,
                    "startTime": 1752532200,
                    "timeZoneOffset": 60
                },
                {
                    "counterId": 30007,
                    "counterValue": 47.0,
                    "dnId": 118748818,
                    "dstOffset": 60,
                    "period": 300,
                    "startTime": 1752532500,
                    "timeZoneOffset": 60
                },
                {
                    "counterId": 30007,
                    "counterValue": 47.0,
                    "dnId": 118748818,
                    "dstOffset": 60,
                    "period": 300,
                    "startTime": 1752532800,
                    "timeZoneOffset": 60
                },
                {
                    "counterId": 30007,
                    "counterValue": 46.0,
                    "dnId": 118748818,
                    "dstOffset": 60,
                    "period": 300,
                    "startTime": 1752533100,
                    "timeZoneOffset": 60
                },
                {
                    "counterId": 30007,
                    "counterValue": 46.0,
                    "dnId": 118748818,
                    "dstOffset": 60,
                    "period": 300,
                    "startTime": 1752533400,
                    "timeZoneOffset": 60
                },
                {
                    "counterId": 30007,
                    "counterValue": 46.0,
                    "dnId": 118748818,
                    "dstOffset": 60,
                    "period": 300,
                    "startTime": 1752533700,
                    "timeZoneOffset": 60
                },
                {
                    "counterId": 30007,
                    "counterValue": 45.0,
                    "dnId": 118748818,
                    "dstOffset": 60,
                    "period": 300,
                    "startTime": 1752534000,
                    "timeZoneOffset": 60
                },
                {
                    "counterId": 30007,
                    "counterValue": 45.0,
                    "dnId": 118748818,
                    "dstOffset": 60,
                    "period": 300,
                    "startTime": 1752534300,
                    "timeZoneOffset": 60
                },
                {
                    "counterId": 30007,
                    "counterValue": 45.0,
                    "dnId": 118748818,
                    "dstOffset": 60,
                    "period": 300,
                    "startTime": 1752534600,
                    "timeZoneOffset": 60
                },
                {
                    "counterId": 30007,
                    "counterValue": 44.0,
                    "dnId": 118748818,
                    "dstOffset": 60,
                    "period": 300,
                    "startTime": 1752534900,
                    "timeZoneOffset": 60
                },
                {
                    "counterId": 30007,
                    "counterValue": 44.0,
                    "dnId": 118748818,
                    "dstOffset": 60,
                    "period": 300,
                    "startTime": 1752535200,
                    "timeZoneOffset": 60
                },
                {
                    "counterId": 30007,
                    "counterValue": 44.0,
                    "dnId": 118748818,
                    "dstOffset": 60,
                    "period": 300,
                    "startTime": 1752535500,
                    "timeZoneOffset": 60
                },
                {
                    "counterId": 30007,
                    "counterValue": 43.0,
                    "dnId": 118748818,
                    "dstOffset": 60,
                    "period": 300,
                    "startTime": 1752535800,
                    "timeZoneOffset": 60
                },
                {
                    "counterId": 30007,
                    "counterValue": 43.0,
                    "dnId": 118748818,
                    "dstOffset": 60,
                    "period": 300,
                    "startTime": 1752536100,
                    "timeZoneOffset": 60
                },
                {
                    "counterId": 30007,
                    "counterValue": 43.0,
                    "dnId": 118748818,
                    "dstOffset": 60,
                    "period": 300,
                    "startTime": 1752536400,
                    "timeZoneOffset": 60
                },
                {
                    "counterId": 30007,
                    "counterValue": 43.0,
                    "dnId": 118748818,
                    "dstOffset": 60,
                    "period": 300,
                    "startTime": 1752536700,
                    "timeZoneOffset": 60
                },
                {
                    "counterId": 30007,
                    "counterValue": 43.0,
                    "dnId": 118748818,
                    "dstOffset": 60,
                    "period": 300,
                    "startTime": 1752537000,
                    "timeZoneOffset": 60
                },
                {
                    "counterId": 30007,
                    "counterValue": 42.0,
                    "dnId": 118748818,
                    "dstOffset": 60,
                    "period": 300,
                    "startTime": 1752537300,
                    "timeZoneOffset": 60
                },
                {
                    "counterId": 30007,
                    "counterValue": 42.0,
                    "dnId": 118748818,
                    "dstOffset": 60,
                    "period": 300,
                    "startTime": 1752537600,
                    "timeZoneOffset": 60
                },
                {
                    "counterId": 30007,
                    "counterValue": 42.0,
                    "dnId": 118748818,
                    "dstOffset": 60,
                    "period": 300,
                    "startTime": 1752537900,
                    "timeZoneOffset": 60
                },
                {
                    "counterId": 30007,
                    "counterValue": 41.0,
                    "dnId": 118748818,
                    "dstOffset": 60,
                    "period": 300,
                    "startTime": 1752538200,
                    "timeZoneOffset": 60
                },
                {
                    "counterId": 30007,
                    "counterValue": 41.0,
                    "dnId": 118748818,
                    "dstOffset": 60,
                    "period": 300,
                    "startTime": 1752538500,
                    "timeZoneOffset": 60
                },
                {
                    "counterId": 30007,
                    "counterValue": 41.0,
                    "dnId": 118748818,
                    "dstOffset": 60,
                    "period": 300,
                    "startTime": 1752538800,
                    "timeZoneOffset": 60
                },
                {
                    "counterId": 30007,
                    "counterValue": 41.0,
                    "dnId": 118748818,
                    "dstOffset": 60,
                    "period": 300,
                    "startTime": 1752539100,
                    "timeZoneOffset": 60
                },
                {
                    "counterId": 30007,
                    "counterValue": 41.0,
                    "dnId": 118748818,
                    "dstOffset": 60,
                    "period": 300,
                    "startTime": 1752539400,
                    "timeZoneOffset": 60
                },
                {
                    "counterId": 30007,
                    "counterValue": 40.0,
                    "dnId": 118748818,
                    "dstOffset": 60,
                    "period": 300,
                    "startTime": 1752539700,
                    "timeZoneOffset": 60
                },
                {
                    "counterId": 30007,
                    "counterValue": 40.0,
                    "dnId": 118748818,
                    "dstOffset": 60,
                    "period": 300,
                    "startTime": 1752540000,
                    "timeZoneOffset": 60
                },
                {
                    "counterId": 30007,
                    "counterValue": 40.0,
                    "dnId": 118748818,
                    "dstOffset": 60,
                    "period": 300,
                    "startTime": 1752540300,
                    "timeZoneOffset": 60
                },
                {
                    "counterId": 30007,
                    "counterValue": 40.0,
                    "dnId": 118748818,
                    "dstOffset": 60,
                    "period": 300,
                    "startTime": 1752540600,
                    "timeZoneOffset": 60
                },
                {
                    "counterId": 30007,
                    "counterValue": 40.0,
                    "dnId": 118748818,
                    "dstOffset": 60,
                    "period": 300,
                    "startTime": 1752540900,
                    "timeZoneOffset": 60
                },
                {
                    "counterId": 30007,
                    "counterValue": 40.0,
                    "dnId": 118748818,
                    "dstOffset": 60,
                    "period": 300,
                    "startTime": 1752541200,
                    "timeZoneOffset": 60
                },
                {
                    "counterId": 30007,
                    "counterValue": 39.0,
                    "dnId": 118748818,
                    "dstOffset": 60,
                    "period": 300,
                    "startTime": 1752541500,
                    "timeZoneOffset": 60
                },
                {
                    "counterId": 30007,
                    "counterValue": 39.0,
                    "dnId": 118748818,
                    "dstOffset": 60,
                    "period": 300,
                    "startTime": 1752541800,
                    "timeZoneOffset": 60
                },
                {
                    "counterId": 30007,
                    "counterValue": 39.0,
                    "dnId": 118748818,
                    "dstOffset": 60,
                    "period": 300,
                    "startTime": 1752542100,
                    "timeZoneOffset": 60
                },
                {
                    "counterId": 30007,
                    "counterValue": 39.0,
                    "dnId": 118748818,
                    "dstOffset": 60,
                    "period": 300,
                    "startTime": 1752542400,
                    "timeZoneOffset": 60
                },
                {
                    "counterId": 30007,
                    "counterValue": 38.0,
                    "dnId": 118748818,
                    "dstOffset": 60,
                    "period": 300,
                    "startTime": 1752542700,
                    "timeZoneOffset": 60
                },
                {
                    "counterId": 30007,
                    "counterValue": 38.0,
                    "dnId": 118748818,
                    "dstOffset": 60,
                    "period": 300,
                    "startTime": 1752543000,
                    "timeZoneOffset": 60
                },
                {
                    "counterId": 30007,
                    "counterValue": 38.0,
                    "dnId": 118748818,
                    "dstOffset": 60,
                    "period": 300,
                    "startTime": 1752543300,
                    "timeZoneOffset": 60
                },
                {
                    "counterId": 30007,
                    "counterValue": 38.0,
                    "dnId": 118748818,
                    "dstOffset": 60,
                    "period": 300,
                    "startTime": 1752543600,
                    "timeZoneOffset": 60
                },
                {
                    "counterId": 30007,
                    "counterValue": 38.0,
                    "dnId": 118748818,
                    "dstOffset": 60,
                    "period": 300,
                    "startTime": 1752543900,
                    "timeZoneOffset": 60
                },
                {
                    "counterId": 30007,
                    "counterValue": 37.0,
                    "dnId": 118748818,
                    "dstOffset": 60,
                    "period": 300,
                    "startTime": 1752544200,
                    "timeZoneOffset": 60
                },
                {
                    "counterId": 30007,
                    "counterValue": 37.0,
                    "dnId": 118748818,
                    "dstOffset": 60,
                    "period": 300,
                    "startTime": 1752544500,
                    "timeZoneOffset": 60
                },
                {
                    "counterId": 30007,
                    "counterValue": 37.0,
                    "dnId": 118748818,
                    "dstOffset": 60,
                    "period": 300,
                    "startTime": 1752544800,
                    "timeZoneOffset": 60
                },
                {
                    "counterId": 30007,
                    "counterValue": 37.0,
                    "dnId": 118748818,
                    "dstOffset": 60,
                    "period": 300,
                    "startTime": 1752545100,
                    "timeZoneOffset": 60
                },
                {
                    "counterId": 30007,
                    "counterValue": 37.0,
                    "dnId": 118748818,
                    "dstOffset": 60,
                    "period": 300,
                    "startTime": 1752545400,
                    "timeZoneOffset": 60
                },
                {
                    "counterId": 30007,
                    "counterValue": 36.0,
                    "dnId": 118748818,
                    "dstOffset": 60,
                    "period": 300,
                    "startTime": 1752545700,
                    "timeZoneOffset": 60
                },
                {
                    "counterId": 30007,
                    "counterValue": 36.0,
                    "dnId": 118748818,
                    "dstOffset": 60,
                    "period": 300,
                    "startTime": 1752546000,
                    "timeZoneOffset": 60
                },
                {
                    "counterId": 30007,
                    "counterValue": 36.0,
                    "dnId": 118748818,
                    "dstOffset": 60,
                    "period": 300,
                    "startTime": 1752546300,
                    "timeZoneOffset": 60
                },
                {
                    "counterId": 30007,
                    "counterValue": 36.0,
                    "dnId": 118748818,
                    "dstOffset": 60,
                    "period": 300,
                    "startTime": 1752546600,
                    "timeZoneOffset": 60
                },
                {
                    "counterId": 30007,
                    "counterValue": 36.0,
                    "dnId": 118748818,
                    "dstOffset": 60,
                    "period": 300,
                    "startTime": 1752546900,
                    "timeZoneOffset": 60
                },
                {
                    "counterId": 30007,
                    "counterValue": 35.0,
                    "dnId": 118748818,
                    "dstOffset": 60,
                    "period": 300,
                    "startTime": 1752547200,
                    "timeZoneOffset": 60
                },
                {
                    "counterId": 30007,
                    "counterValue": 35.0,
                    "dnId": 118748818,
                    "dstOffset": 60,
                    "period": 300,
                    "startTime": 1752547500,
                    "timeZoneOffset": 60
                },
                {
                    "counterId": 30007,
                    "counterValue": 35.0,
                    "dnId": 118748818,
                    "dstOffset": 60,
                    "period": 300,
                    "startTime": 1752547800,
                    "timeZoneOffset": 60
                },
                {
                    "counterId": 30007,
                    "counterValue": 35.0,
                    "dnId": 118748818,
                    "dstOffset": 60,
                    "period": 300,
                    "startTime": 1752548100,
                    "timeZoneOffset": 60
                },
                {
                    "counterId": 30007,
                    "counterValue": 35.0,
                    "dnId": 118748818,
                    "dstOffset": 60,
                    "period": 300,
                    "startTime": 1752548400,
                    "timeZoneOffset": 60
                },
                {
                    "counterId": 30007,
                    "counterValue": 35.0,
                    "dnId": 118748818,
                    "dstOffset": 60,
                    "period": 300,
                    "startTime": 1752548700,
                    "timeZoneOffset": 60
                },
                {
                    "counterId": 30007,
                    "counterValue": 35.0,
                    "dnId": 118748818,
                    "dstOffset": 60,
                    "period": 300,
                    "startTime": 1752549000,
                    "timeZoneOffset": 60
                },
                {
                    "counterId": 30007,
                    "counterValue": 35.0,
                    "dnId": 118748818,
                    "dstOffset": 60,
                    "period": 300,
                    "startTime": 1752549300,
                    "timeZoneOffset": 60
                },
                {
                    "counterId": 30007,
                    "counterValue": 34.0,
                    "dnId": 118748818,
                    "dstOffset": 60,
                    "period": 300,
                    "startTime": 1752549600,
                    "timeZoneOffset": 60
                },
                {
                    "counterId": 30007,
                    "counterValue": 34.0,
                    "dnId": 118748818,
                    "dstOffset": 60,
                    "period": 300,
                    "startTime": 1752549900,
                    "timeZoneOffset": 60
                },
                {
                    "counterId": 30007,
                    "counterValue": 34.0,
                    "dnId": 118748818,
                    "dstOffset": 60,
                    "period": 300,
                    "startTime": 1752550200,
                    "timeZoneOffset": 60
                },
                {
                    "counterId": 30007,
                    "counterValue": 34.0,
                    "dnId": 118748818,
                    "dstOffset": 60,
                    "period": 300,
                    "startTime": 1752550500,
                    "timeZoneOffset": 60
                },
                {
                    "counterId": 30007,
                    "counterValue": 34.0,
                    "dnId": 118748818,
                    "dstOffset": 60,
                    "period": 300,
                    "startTime": 1752550800,
                    "timeZoneOffset": 60
                },
                {
                    "counterId": 30007,
                    "counterValue": 34.0,
                    "dnId": 118748818,
                    "dstOffset": 60,
                    "period": 300,
                    "startTime": 1752551100,
                    "timeZoneOffset": 60
                },
                {
                    "counterId": 30007,
                    "counterValue": 34.0,
                    "dnId": 118748818,
                    "dstOffset": 60,
                    "period": 300,
                    "startTime": 1752551400,
                    "timeZoneOffset": 60
                },
                {
                    "counterId": 30007,
                    "counterValue": 33.0,
                    "dnId": 118748818,
                    "dstOffset": 60,
                    "period": 300,
                    "startTime": 1752551700,
                    "timeZoneOffset": 60
                },
                {
                    "counterId": 30007,
                    "counterValue": 33.0,
                    "dnId": 118748818,
                    "dstOffset": 60,
                    "period": 300,
                    "startTime": 1752552000,
                    "timeZoneOffset": 60
                },
                {
                    "counterId": 30007,
                    "counterValue": 33.0,
                    "dnId": 118748818,
                    "dstOffset": 60,
                    "period": 300,
                    "startTime": 1752552300,
                    "timeZoneOffset": 60
                },
                {
                    "counterId": 30007,
                    "counterValue": 33.0,
                    "dnId": 118748818,
                    "dstOffset": 60,
                    "period": 300,
                    "startTime": 1752552600,
                    "timeZoneOffset": 60
                },
                {
                    "counterId": 30007,
                    "counterValue": 33.0,
                    "dnId": 118748818,
                    "dstOffset": 60,
                    "period": 300,
                    "startTime": 1752552900,
                    "timeZoneOffset": 60
                },
                {
                    "counterId": 30007,
                    "counterValue": 33.0,
                    "dnId": 118748818,
                    "dstOffset": 60,
                    "period": 300,
                    "startTime": 1752553200,
                    "timeZoneOffset": 60
                },
                {
                    "counterId": 30007,
                    "counterValue": 33.0,
                    "dnId": 118748818,
                    "dstOffset": 60,
                    "period": 300,
                    "startTime": 1752553500,
                    "timeZoneOffset": 60
                },
                {
                    "counterId": 30007,
                    "counterValue": 33.0,
                    "dnId": 118748818,
                    "dstOffset": 60,
                    "period": 300,
                    "startTime": 1752553800,
                    "timeZoneOffset": 60
                },
                {
                    "counterId": 30007,
                    "counterValue": 33.0,
                    "dnId": 118748818,
                    "dstOffset": 60,
                    "period": 300,
                    "startTime": 1752554100,
                    "timeZoneOffset": 60
                },
                {
                    "counterId": 30007,
                    "counterValue": 33.0,
                    "dnId": 118748818,
                    "dstOffset": 60,
                    "period": 300,
                    "startTime": 1752554400,
                    "timeZoneOffset": 60
                },
                {
                    "counterId": 30007,
                    "counterValue": 33.0,
                    "dnId": 118748818,
                    "dstOffset": 60,
                    "period": 300,
                    "startTime": 1752554700,
                    "timeZoneOffset": 60
                },
                {
                    "counterId": 30007,
                    "counterValue": 33.0,
                    "dnId": 118748818,
                    "dstOffset": 60,
                    "period": 300,
                    "startTime": 1752555000,
                    "timeZoneOffset": 60
                },
                {
                    "counterId": 30007,
                    "counterValue": 33.0,
                    "dnId": 118748818,
                    "dstOffset": 60,
                    "period": 300,
                    "startTime": 1752555300,
                    "timeZoneOffset": 60
                },
                {
                    "counterId": 30007,
                    "counterValue": 33.0,
                    "dnId": 118748818,
                    "dstOffset": 60,
                    "period": 300,
                    "startTime": 1752555600,
                    "timeZoneOffset": 60
                },
                {
                    "counterId": 30007,
                    "counterValue": 33.0,
                    "dnId": 118748818,
                    "dstOffset": 60,
                    "period": 300,
                    "startTime": 1752555900,
                    "timeZoneOffset": 60
                },
                {
                    "counterId": 30007,
                    "counterValue": 33.0,
                    "dnId": 118748818,
                    "dstOffset": 60,
                    "period": 300,
                    "startTime": 1752556200,
                    "timeZoneOffset": 60
                },
                {
                    "counterId": 30007,
                    "counterValue": 33.0,
                    "dnId": 118748818,
                    "dstOffset": 60,
                    "period": 300,
                    "startTime": 1752556500,
                    "timeZoneOffset": 60
                },
                {
                    "counterId": 30007,
                    "counterValue": 33.0,
                    "dnId": 118748818,
                    "dstOffset": 60,
                    "period": 300,
                    "startTime": 1752556800,
                    "timeZoneOffset": 60
                },
                {
                    "counterId": 30007,
                    "counterValue": 33.0,
                    "dnId": 118748818,
                    "dstOffset": 60,
                    "period": 300,
                    "startTime": 1752557100,
                    "timeZoneOffset": 60
                },
                {
                    "counterId": 30007,
                    "counterValue": 33.0,
                    "dnId": 118748818,
                    "dstOffset": 60,
                    "period": 300,
                    "startTime": 1752557400,
                    "timeZoneOffset": 60
                },
                {
                    "counterId": 30007,
                    "counterValue": 33.0,
                    "dnId": 118748818,
                    "dstOffset": 60,
                    "period": 300,
                    "startTime": 1752557700,
                    "timeZoneOffset": 60
                },
                {
                    "counterId": 30007,
                    "counterValue": 32.0,
                    "dnId": 118748818,
                    "dstOffset": 60,
                    "period": 300,
                    "startTime": 1752558000,
                    "timeZoneOffset": 60
                },
                {
                    "counterId": 30007,
                    "counterValue": 32.0,
                    "dnId": 118748818,
                    "dstOffset": 60,
                    "period": 300,
                    "startTime": 1752558300,
                    "timeZoneOffset": 60
                },
                {
                    "counterId": 30007,
                    "counterValue": 31.0,
                    "dnId": 118748818,
                    "dstOffset": 60,
                    "period": 300,
                    "startTime": 1752558600,
                    "timeZoneOffset": 60
                },
                {
                    "counterId": 30007,
                    "counterValue": 31.0,
                    "dnId": 118748818,
                    "dstOffset": 60,
                    "period": 300,
                    "startTime": 1752558900,
                    "timeZoneOffset": 60
                },
                {
                    "counterId": 30007,
                    "counterValue": 31.0,
                    "dnId": 118748818,
                    "dstOffset": 60,
                    "period": 300,
                    "startTime": 1752559200,
                    "timeZoneOffset": 60
                },
                {
                    "counterId": 30007,
                    "counterValue": 31.0,
                    "dnId": 118748818,
                    "dstOffset": 60,
                    "period": 300,
                    "startTime": 1752559500,
                    "timeZoneOffset": 60
                },
                {
                    "counterId": 30007,
                    "counterValue": 32.0,
                    "dnId": 118748818,
                    "dstOffset": 60,
                    "period": 300,
                    "startTime": 1752559800,
                    "timeZoneOffset": 60
                },
                {
                    "counterId": 30007,
                    "counterValue": 32.0,
                    "dnId": 118748818,
                    "dstOffset": 60,
                    "period": 300,
                    "startTime": 1752560100,
                    "timeZoneOffset": 60
                },
                {
                    "counterId": 30007,
                    "counterValue": 33.0,
                    "dnId": 118748818,
                    "dstOffset": 60,
                    "period": 300,
                    "startTime": 1752560400,
                    "timeZoneOffset": 60
                },
                {
                    "counterId": 30007,
                    "counterValue": 35.0,
                    "dnId": 118748818,
                    "dstOffset": 60,
                    "period": 300,
                    "startTime": 1752560700,
                    "timeZoneOffset": 60
                },
                {
                    "counterId": 30007,
                    "counterValue": 36.0,
                    "dnId": 118748818,
                    "dstOffset": 60,
                    "period": 300,
                    "startTime": 1752561000,
                    "timeZoneOffset": 60
                },
                {
                    "counterId": 30007,
                    "counterValue": 37.0,
                    "dnId": 118748818,
                    "dstOffset": 60,
                    "period": 300,
                    "startTime": 1752561300,
                    "timeZoneOffset": 60
                },
                {
                    "counterId": 30007,
                    "counterValue": 37.0,
                    "dnId": 118748818,
                    "dstOffset": 60,
                    "period": 300,
                    "startTime": 1752561600,
                    "timeZoneOffset": 60
                },
                {
                    "counterId": 30007,
                    "counterValue": 37.0,
                    "dnId": 118748818,
                    "dstOffset": 60,
                    "period": 300,
                    "startTime": 1752561900,
                    "timeZoneOffset": 60
                },
                {
                    "counterId": 30007,
                    "counterValue": 36.0,
                    "dnId": 118748818,
                    "dstOffset": 60,
                    "period": 300,
                    "startTime": 1752562200,
                    "timeZoneOffset": 60
                },
                {
                    "counterId": 30007,
                    "counterValue": 36.0,
                    "dnId": 118748818,
                    "dstOffset": 60,
                    "period": 300,
                    "startTime": 1752562500,
                    "timeZoneOffset": 60
                },
                {
                    "counterId": 30007,
                    "counterValue": 36.0,
                    "dnId": 118748818,
                    "dstOffset": 60,
                    "period": 300,
                    "startTime": 1752562800,
                    "timeZoneOffset": 60
                },
                {
                    "counterId": 30007,
                    "counterValue": 37.0,
                    "dnId": 118748818,
                    "dstOffset": 60,
                    "period": 300,
                    "startTime": 1752563100,
                    "timeZoneOffset": 60
                },
                {
                    "counterId": 30007,
                    "counterValue": 41.0,
                    "dnId": 118748818,
                    "dstOffset": 60,
                    "period": 300,
                    "startTime": 1752563400,
                    "timeZoneOffset": 60
                },
                {
                    "counterId": 30007,
                    "counterValue": 43.0,
                    "dnId": 118748818,
                    "dstOffset": 60,
                    "period": 300,
                    "startTime": 1752563700,
                    "timeZoneOffset": 60
                },
                {
                    "counterId": 30007,
                    "counterValue": 46.0,
                    "dnId": 118748818,
                    "dstOffset": 60,
                    "period": 300,
                    "startTime": 1752564000,
                    "timeZoneOffset": 60
                },
                {
                    "counterId": 30007,
                    "counterValue": 49.0,
                    "dnId": 118748818,
                    "dstOffset": 60,
                    "period": 300,
                    "startTime": 1752564300,
                    "timeZoneOffset": 60
                },
                {
                    "counterId": 30007,
                    "counterValue": 52.0,
                    "dnId": 118748818,
                    "dstOffset": 60,
                    "period": 300,
                    "startTime": 1752564600,
                    "timeZoneOffset": 60
                },
                {
                    "counterId": 30007,
                    "counterValue": 55.0,
                    "dnId": 118748818,
                    "dstOffset": 60,
                    "period": 300,
                    "startTime": 1752564900,
                    "timeZoneOffset": 60
                },
                {
                    "counterId": 30007,
                    "counterValue": 58.0,
                    "dnId": 118748818,
                    "dstOffset": 60,
                    "period": 300,
                    "startTime": 1752565200,
                    "timeZoneOffset": 60
                },
                {
                    "counterId": 30007,
                    "counterValue": 62.0,
                    "dnId": 118748818,
                    "dstOffset": 60,
                    "period": 300,
                    "startTime": 1752565500,
                    "timeZoneOffset": 60
                },
                {
                    "counterId": 30007,
                    "counterValue": 65.0,
                    "dnId": 118748818,
                    "dstOffset": 60,
                    "period": 300,
                    "startTime": 1752565800,
                    "timeZoneOffset": 60
                },
                {
                    "counterId": 30007,
                    "counterValue": 68.0,
                    "dnId": 118748818,
                    "dstOffset": 60,
                    "period": 300,
                    "startTime": 1752566100,
                    "timeZoneOffset": 60
                },
                {
                    "counterId": 30007,
                    "counterValue": 70.0,
                    "dnId": 118748818,
                    "dstOffset": 60,
                    "period": 300,
                    "startTime": 1752566400,
                    "timeZoneOffset": 60
                },
                {
                    "counterId": 30007,
                    "counterValue": 73.0,
                    "dnId": 118748818,
                    "dstOffset": 60,
                    "period": 300,
                    "startTime": 1752566700,
                    "timeZoneOffset": 60
                },
                {
                    "counterId": 30007,
                    "counterValue": 75.0,
                    "dnId": 118748818,
                    "dstOffset": 60,
                    "period": 300,
                    "startTime": 1752567000,
                    "timeZoneOffset": 60
                },
                {
                    "counterId": 30007,
                    "counterValue": 78.0,
                    "dnId": 118748818,
                    "dstOffset": 60,
                    "period": 300,
                    "startTime": 1752567300,
                    "timeZoneOffset": 60
                },
                {
                    "counterId": 30007,
                    "counterValue": 81.0,
                    "dnId": 118748818,
                    "dstOffset": 60,
                    "period": 300,
                    "startTime": 1752567600,
                    "timeZoneOffset": 60
                },
                {
                    "counterId": 30007,
                    "counterValue": 82.0,
                    "dnId": 118748818,
                    "dstOffset": 60,
                    "period": 300,
                    "startTime": 1752567900,
                    "timeZoneOffset": 60
                },
                {
                    "counterId": 30007,
                    "counterValue": 83.0,
                    "dnId": 118748818,
                    "dstOffset": 60,
                    "period": 300,
                    "startTime": 1752568200,
                    "timeZoneOffset": 60
                },
                {
                    "counterId": 30007,
                    "counterValue": 86.0,
                    "dnId": 118748818,
                    "dstOffset": 60,
                    "period": 300,
                    "startTime": 1752568500,
                    "timeZoneOffset": 60
                },
                {
                    "counterId": 30007,
                    "counterValue": 88.0,
                    "dnId": 118748818,
                    "dstOffset": 60,
                    "period": 300,
                    "startTime": 1752568800,
                    "timeZoneOffset": 60
                },
                {
                    "counterId": 30007,
                    "counterValue": 91.0,
                    "dnId": 118748818,
                    "dstOffset": 60,
                    "period": 300,
                    "startTime": 1752569100,
                    "timeZoneOffset": 60
                },
                {
                    "counterId": 30007,
                    "counterValue": 94.0,
                    "dnId": 118748818,
                    "dstOffset": 60,
                    "period": 300,
                    "startTime": 1752569400,
                    "timeZoneOffset": 60
                },
                {
                    "counterId": 30007,
                    "counterValue": 98.0,
                    "dnId": 118748818,
                    "dstOffset": 60,
                    "period": 300,
                    "startTime": 1752569700,
                    "timeZoneOffset": 60
                },
                {
                    "counterId": 30007,
                    "counterValue": 100.0,
                    "dnId": 118748818,
                    "dstOffset": 60,
                    "period": 300,
                    "startTime": 1752570000,
                    "timeZoneOffset": 60
                },
                {
                    "counterId": 30007,
                    "counterValue": 100.0,
                    "dnId": 118748818,
                    "dstOffset": 60,
                    "period": 300,
                    "startTime": 1752570300,
                    "timeZoneOffset": 60
                },
                {
                    "counterId": 30007,
                    "counterValue": 100.0,
                    "dnId": 118748818,
                    "dstOffset": 60,
                    "period": 300,
                    "startTime": 1752570600,
                    "timeZoneOffset": 60
                },
                {
                    "counterId": 30007,
                    "counterValue": 100.0,
                    "dnId": 118748818,
                    "dstOffset": 60,
                    "period": 300,
                    "startTime": 1752570900,
                    "timeZoneOffset": 60
                },
                {
                    "counterId": 30007,
                    "counterValue": 100.0,
                    "dnId": 118748818,
                    "dstOffset": 60,
                    "period": 300,
                    "startTime": 1752571200,
                    "timeZoneOffset": 60
                },
                {
                    "counterId": 30007,
                    "counterValue": 100.0,
                    "dnId": 118748818,
                    "dstOffset": 60,
                    "period": 300,
                    "startTime": 1752571500,
                    "timeZoneOffset": 60
                },
                {
                    "counterId": 30007,
                    "counterValue": 100.0,
                    "dnId": 118748818,
                    "dstOffset": 60,
                    "period": 300,
                    "startTime": 1752571800,
                    "timeZoneOffset": 60
                },
                {
                    "counterId": 30007,
                    "counterValue": 100.0,
                    "dnId": 118748818,
                    "dstOffset": 60,
                    "period": 300,
                    "startTime": 1752572100,
                    "timeZoneOffset": 60
                },
                {
                    "counterId": 30007,
                    "counterValue": 100.0,
                    "dnId": 118748818,
                    "dstOffset": 60,
                    "period": 300,
                    "startTime": 1752572400,
                    "timeZoneOffset": 60
                },
                {
                    "counterId": 30007,
                    "counterValue": 100.0,
                    "dnId": 118748818,
                    "dstOffset": 60,
                    "period": 300,
                    "startTime": 1752572700,
                    "timeZoneOffset": 60
                },
                {
                    "counterId": 30007,
                    "counterValue": 100.0,
                    "dnId": 118748818,
                    "dstOffset": 60,
                    "period": 300,
                    "startTime": 1752573000,
                    "timeZoneOffset": 60
                },
                {
                    "counterId": 30007,
                    "counterValue": 100.0,
                    "dnId": 118748818,
                    "dstOffset": 60,
                    "period": 300,
                    "startTime": 1752573300,
                    "timeZoneOffset": 60
                },
                {
                    "counterId": 30007,
                    "counterValue": 100.0,
                    "dnId": 118748818,
                    "dstOffset": 60,
                    "period": 300,
                    "startTime": 1752573600,
                    "timeZoneOffset": 60
                },
                {
                    "counterId": 30007,
                    "counterValue": 100.0,
                    "dnId": 118748818,
                    "dstOffset": 60,
                    "period": 300,
                    "startTime": 1752573900,
                    "timeZoneOffset": 60
                },
                {
                    "counterId": 30007,
                    "counterValue": 100.0,
                    "dnId": 118748818,
                    "dstOffset": 60,
                    "period": 300,
                    "startTime": 1752574200,
                    "timeZoneOffset": 60
                },
                {
                    "counterId": 30007,
                    "counterValue": 100.0,
                    "dnId": 118748818,
                    "dstOffset": 60,
                    "period": 300,
                    "startTime": 1752574500,
                    "timeZoneOffset": 60
                },
                {
                    "counterId": 30007,
                    "counterValue": 100.0,
                    "dnId": 118748818,
                    "dstOffset": 60,
                    "period": 300,
                    "startTime": 1752574800,
                    "timeZoneOffset": 60
                },
                {
                    "counterId": 30007,
                    "counterValue": 100.0,
                    "dnId": 118748818,
                    "dstOffset": 60,
                    "period": 300,
                    "startTime": 1752575100,
                    "timeZoneOffset": 60
                },
                {
                    "counterId": 30007,
                    "counterValue": 100.0,
                    "dnId": 118748818,
                    "dstOffset": 60,
                    "period": 300,
                    "startTime": 1752575400,
                    "timeZoneOffset": 60
                },
                {
                    "counterId": 30007,
                    "counterValue": 100.0,
                    "dnId": 118748818,
                    "dstOffset": 60,
                    "period": 300,
                    "startTime": 1752575700,
                    "timeZoneOffset": 60
                },
                {
                    "counterId": 30007,
                    "counterValue": 100.0,
                    "dnId": 118748818,
                    "dstOffset": 60,
                    "period": 300,
                    "startTime": 1752576000,
                    "timeZoneOffset": 60
                },
                {
                    "counterId": 30007,
                    "counterValue": 100.0,
                    "dnId": 118748818,
                    "dstOffset": 60,
                    "period": 300,
                    "startTime": 1752576300,
                    "timeZoneOffset": 60
                },
                {
                    "counterId": 30007,
                    "counterValue": 100.0,
                    "dnId": 118748818,
                    "dstOffset": 60,
                    "period": 300,
                    "startTime": 1752576600,
                    "timeZoneOffset": 60
                },
                {
                    "counterId": 30007,
                    "counterValue": 100.0,
                    "dnId": 118748818,
                    "dstOffset": 60,
                    "period": 300,
                    "startTime": 1752576900,
                    "timeZoneOffset": 60
                },
                {
                    "counterId": 30007,
                    "counterValue": 100.0,
                    "dnId": 118748818,
                    "dstOffset": 60,
                    "period": 300,
                    "startTime": 1752577200,
                    "timeZoneOffset": 60
                },
                {
                    "counterId": 30007,
                    "counterValue": 100.0,
                    "dnId": 118748818,
                    "dstOffset": 60,
                    "period": 300,
                    "startTime": 1752577500,
                    "timeZoneOffset": 60
                },
                {
                    "counterId": 30007,
                    "counterValue": 100.0,
                    "dnId": 118748818,
                    "dstOffset": 60,
                    "period": 300,
                    "startTime": 1752577800,
                    "timeZoneOffset": 60
                },
                {
                    "counterId": 30007,
                    "counterValue": 100.0,
                    "dnId": 118748818,
                    "dstOffset": 60,
                    "period": 300,
                    "startTime": 1752578100,
                    "timeZoneOffset": 60
                },
                {
                    "counterId": 30007,
                    "counterValue": 100.0,
                    "dnId": 118748818,
                    "dstOffset": 60,
                    "period": 300,
                    "startTime": 1752578400,
                    "timeZoneOffset": 60
                },
                {
                    "counterId": 30007,
                    "counterValue": 100.0,
                    "dnId": 118748818,
                    "dstOffset": 60,
                    "period": 300,
                    "startTime": 1752578700,
                    "timeZoneOffset": 60
                },
                {
                    "counterId": 30007,
                    "counterValue": 100.0,
                    "dnId": 118748818,
                    "dstOffset": 60,
                    "period": 300,
                    "startTime": 1752579000,
                    "timeZoneOffset": 60
                },
                {
                    "counterId": 30007,
                    "counterValue": 99.0,
                    "dnId": 118748818,
                    "dstOffset": 60,
                    "period": 300,
                    "startTime": 1752579300,
                    "timeZoneOffset": 60
                },
                {
                    "counterId": 30007,
                    "counterValue": 99.0,
                    "dnId": 118748818,
                    "dstOffset": 60,
                    "period": 300,
                    "startTime": 1752579600,
                    "timeZoneOffset": 60
                },
                {
                    "counterId": 30007,
                    "counterValue": 100.0,
                    "dnId": 118748818,
                    "dstOffset": 60,
                    "period": 300,
                    "startTime": 1752579900,
                    "timeZoneOffset": 60
                },
                {
                    "counterId": 30007,
                    "counterValue": 100.0,
                    "dnId": 118748818,
                    "dstOffset": 60,
                    "period": 300,
                    "startTime": 1752580200,
                    "timeZoneOffset": 60
                },
                {
                    "counterId": 30007,
                    "counterValue": 100.0,
                    "dnId": 118748818,
                    "dstOffset": 60,
                    "period": 300,
                    "startTime": 1752580500,
                    "timeZoneOffset": 60
                },
                {
                    "counterId": 30007,
                    "counterValue": 100.0,
                    "dnId": 118748818,
                    "dstOffset": 60,
                    "period": 300,
                    "startTime": 1752580800,
                    "timeZoneOffset": 60
                },
                {
                    "counterId": 30007,
                    "counterValue": 100.0,
                    "dnId": 118748818,
                    "dstOffset": 60,
                    "period": 300,
                    "startTime": 1752581100,
                    "timeZoneOffset": 60
                },
                {
                    "counterId": 30007,
                    "counterValue": 100.0,
                    "dnId": 118748818,
                    "dstOffset": 60,
                    "period": 300,
                    "startTime": 1752581400,
                    "timeZoneOffset": 60
                },
                {
                    "counterId": 30007,
                    "counterValue": 100.0,
                    "dnId": 118748818,
                    "dstOffset": 60,
                    "period": 300,
                    "startTime": 1752581700,
                    "timeZoneOffset": 60
                },
                {
                    "counterId": 30007,
                    "counterValue": 100.0,
                    "dnId": 118748818,
                    "dstOffset": 60,
                    "period": 300,
                    "startTime": 1752582000,
                    "timeZoneOffset": 60
                },
                {
                    "counterId": 30007,
                    "counterValue": 100.0,
                    "dnId": 118748818,
                    "dstOffset": 60,
                    "period": 300,
                    "startTime": 1752582300,
                    "timeZoneOffset": 60
                },
                {
                    "counterId": 30007,
                    "counterValue": 100.0,
                    "dnId": 118748818,
                    "dstOffset": 60,
                    "period": 300,
                    "startTime": 1752582600,
                    "timeZoneOffset": 60
                },
                {
                    "counterId": 30007,
                    "counterValue": 100.0,
                    "dnId": 118748818,
                    "dstOffset": 60,
                    "period": 300,
                    "startTime": 1752582900,
                    "timeZoneOffset": 60
                },
                {
                    "counterId": 30007,
                    "counterValue": 100.0,
                    "dnId": 118748818,
                    "dstOffset": 60,
                    "period": 300,
                    "startTime": 1752583200,
                    "timeZoneOffset": 60
                },
                {
                    "counterId": 30007,
                    "counterValue": 100.0,
                    "dnId": 118748818,
                    "dstOffset": 60,
                    "period": 300,
                    "startTime": 1752583500,
                    "timeZoneOffset": 60
                },
                {
                    "counterId": 30007,
                    "counterValue": 100.0,
                    "dnId": 118748818,
                    "dstOffset": 60,
                    "period": 300,
                    "startTime": 1752583800,
                    "timeZoneOffset": 60
                },
                {
                    "counterId": 30007,
                    "counterValue": 100.0,
                    "dnId": 118748818,
                    "dstOffset": 60,
                    "period": 300,
                    "startTime": 1752584100,
                    "timeZoneOffset": 60
                },
                {
                    "counterId": 30007,
                    "counterValue": 100.0,
                    "dnId": 118748818,
                    "dstOffset": 60,
                    "period": 300,
                    "startTime": 1752584400,
                    "timeZoneOffset": 60
                },
                {
                    "counterId": 30007,
                    "counterValue": 100.0,
                    "dnId": 118748818,
                    "dstOffset": 60,
                    "period": 300,
                    "startTime": 1752584700,
                    "timeZoneOffset": 60
                },
                {
                    "counterId": 30007,
                    "counterValue": 100.0,
                    "dnId": 118748818,
                    "dstOffset": 60,
                    "period": 300,
                    "startTime": 1752585000,
                    "timeZoneOffset": 60
                },
                {
                    "counterId": 30007,
                    "counterValue": 100.0,
                    "dnId": 118748818,
                    "dstOffset": 60,
                    "period": 300,
                    "startTime": 1752585300,
                    "timeZoneOffset": 60
                },
                {
                    "counterId": 30007,
                    "counterValue": 100.0,
                    "dnId": 118748818,
                    "dstOffset": 60,
                    "period": 300,
                    "startTime": 1752585600,
                    "timeZoneOffset": 60
                },
                {
                    "counterId": 30007,
                    "counterValue": 100.0,
                    "dnId": 118748818,
                    "dstOffset": 60,
                    "period": 300,
                    "startTime": 1752585900,
                    "timeZoneOffset": 60
                },
                {
                    "counterId": 30007,
                    "counterValue": 100.0,
                    "dnId": 118748818,
                    "dstOffset": 60,
                    "period": 300,
                    "startTime": 1752586200,
                    "timeZoneOffset": 60
                },
                {
                    "counterId": 30007,
                    "counterValue": 100.0,
                    "dnId": 118748818,
                    "dstOffset": 60,
                    "period": 300,
                    "startTime": 1752586500,
                    "timeZoneOffset": 60
                },
                {
                    "counterId": 30007,
                    "counterValue": 100.0,
                    "dnId": 118748818,
                    "dstOffset": 60,
                    "period": 300,
                    "startTime": 1752586800,
                    "timeZoneOffset": 60
                },
                {
                    "counterId": 30007,
                    "counterValue": 100.0,
                    "dnId": 118748818,
                    "dstOffset": 60,
                    "period": 300,
                    "startTime": 1752587100,
                    "timeZoneOffset": 60
                },
                {
                    "counterId": 30007,
                    "counterValue": 100.0,
                    "dnId": 118748818,
                    "dstOffset": 60,
                    "period": 300,
                    "startTime": 1752587400,
                    "timeZoneOffset": 60
                },
                {
                    "counterId": 30007,
                    "counterValue": 100.0,
                    "dnId": 118748818,
                    "dstOffset": 60,
                    "period": 300,
                    "startTime": 1752587700,
                    "timeZoneOffset": 60
                },
                {
                    "counterId": 30007,
                    "counterValue": 100.0,
                    "dnId": 118748818,
                    "dstOffset": 60,
                    "period": 300,
                    "startTime": 1752588000,
                    "timeZoneOffset": 60
                },
                {
                    "counterId": 30007,
                    "counterValue": 100.0,
                    "dnId": 118748818,
                    "dstOffset": 60,
                    "period": 300,
                    "startTime": 1752588300,
                    "timeZoneOffset": 60
                },
                {
                    "counterId": 30007,
                    "counterValue": 100.0,
                    "dnId": 118748818,
                    "dstOffset": 60,
                    "period": 300,
                    "startTime": 1752588600,
                    "timeZoneOffset": 60
                },
                {
                    "counterId": 30007,
                    "counterValue": 100.0,
                    "dnId": 118748818,
                    "dstOffset": 60,
                    "period": 300,
                    "startTime": 1752588900,
                    "timeZoneOffset": 60
                },
                {
                    "counterId": 30007,
                    "counterValue": 100.0,
                    "dnId": 118748818,
                    "dstOffset": 60,
                    "period": 300,
                    "startTime": 1752589200,
                    "timeZoneOffset": 60
                },
                {
                    "counterId": 30007,
                    "counterValue": 100.0,
                    "dnId": 118748818,
                    "dstOffset": 60,
                    "period": 300,
                    "startTime": 1752589500,
                    "timeZoneOffset": 60
                },
                {
                    "counterId": 30007,
                    "counterValue": 100.0,
                    "dnId": 118748818,
                    "dstOffset": 60,
                    "period": 300,
                    "startTime": 1752589800,
                    "timeZoneOffset": 60
                },
                {
                    "counterId": 30007,
                    "counterValue": 100.0,
                    "dnId": 118748818,
                    "dstOffset": 60,
                    "period": 300,
                    "startTime": 1752590100,
                    "timeZoneOffset": 60
                },
                {
                    "counterId": 30007,
                    "counterValue": 100.0,
                    "dnId": 118748818,
                    "dstOffset": 60,
                    "period": 300,
                    "startTime": 1752590400,
                    "timeZoneOffset": 60
                },
                {
                    "counterId": 30007,
                    "counterValue": 100.0,
                    "dnId": 118748818,
                    "dstOffset": 60,
                    "period": 300,
                    "startTime": 1752590700,
                    "timeZoneOffset": 60
                },
                {
                    "counterId": 30007,
                    "counterValue": 100.0,
                    "dnId": 118748818,
                    "dstOffset": 60,
                    "period": 300,
                    "startTime": 1752591000,
                    "timeZoneOffset": 60
                },
                {
                    "counterId": 30007,
                    "counterValue": 99.0,
                    "dnId": 118748818,
                    "dstOffset": 60,
                    "period": 300,
                    "startTime": 1752591300,
                    "timeZoneOffset": 60
                },
                {
                    "counterId": 30007,
                    "counterValue": 100.0,
                    "dnId": 118748818,
                    "dstOffset": 60,
                    "period": 300,
                    "startTime": 1752591600,
                    "timeZoneOffset": 60
                },
                {
                    "counterId": 30007,
                    "counterValue": 100.0,
                    "dnId": 118748818,
                    "dstOffset": 60,
                    "period": 300,
                    "startTime": 1752591900,
                    "timeZoneOffset": 60
                },
                {
                    "counterId": 30007,
                    "counterValue": 100.0,
                    "dnId": 118748818,
                    "dstOffset": 60,
                    "period": 300,
                    "startTime": 1752592200,
                    "timeZoneOffset": 60
                },
                {
                    "counterId": 30007,
                    "counterValue": 100.0,
                    "dnId": 118748818,
                    "dstOffset": 60,
                    "period": 300,
                    "startTime": 1752592500,
                    "timeZoneOffset": 60
                },
                {
                    "counterId": 30007,
                    "counterValue": 100.0,
                    "dnId": 118748818,
                    "dstOffset": 60,
                    "period": 300,
                    "startTime": 1752592800,
                    "timeZoneOffset": 60
                },
                {
                    "counterId": 30007,
                    "counterValue": 100.0,
                    "dnId": 118748818,
                    "dstOffset": 60,
                    "period": 300,
                    "startTime": 1752593100,
                    "timeZoneOffset": 60
                },
                {
                    "counterId": 30007,
                    "counterValue": 100.0,
                    "dnId": 118748818,
                    "dstOffset": 60,
                    "period": 300,
                    "startTime": 1752593400,
                    "timeZoneOffset": 60
                },
                {
                    "counterId": 30007,
                    "counterValue": 100.0,
                    "dnId": 118748818,
                    "dstOffset": 60,
                    "period": 300,
                    "startTime": 1752593700,
                    "timeZoneOffset": 60
                },
                {
                    "counterId": 30007,
                    "counterValue": 100.0,
                    "dnId": 118748818,
                    "dstOffset": 60,
                    "period": 300,
                    "startTime": 1752594000,
                    "timeZoneOffset": 60
                },
                {
                    "counterId": 30007,
                    "counterValue": 100.0,
                    "dnId": 118748818,
                    "dstOffset": 60,
                    "period": 300,
                    "startTime": 1752594300,
                    "timeZoneOffset": 60
                },
                {
                    "counterId": 30007,
                    "counterValue": 100.0,
                    "dnId": 118748818,
                    "dstOffset": 60,
                    "period": 300,
                    "startTime": 1752594600,
                    "timeZoneOffset": 60
                },
                {
                    "counterId": 30007,
                    "counterValue": 100.0,
                    "dnId": 118748818,
                    "dstOffset": 60,
                    "period": 300,
                    "startTime": 1752594900,
                    "timeZoneOffset": 60
                },
                {
                    "counterId": 30007,
                    "counterValue": 100.0,
                    "dnId": 118748818,
                    "dstOffset": 60,
                    "period": 300,
                    "startTime": 1752595200,
                    "timeZoneOffset": 60
                },
                {
                    "counterId": 30007,
                    "counterValue": 100.0,
                    "dnId": 118748818,
                    "dstOffset": 60,
                    "period": 300,
                    "startTime": 1752595500,
                    "timeZoneOffset": 60
                },
                {
                    "counterId": 30007,
                    "counterValue": 100.0,
                    "dnId": 118748818,
                    "dstOffset": 60,
                    "period": 300,
                    "startTime": 1752595800,
                    "timeZoneOffset": 60
                },
                {
                    "counterId": 30007,
                    "counterValue": 100.0,
                    "dnId": 118748818,
                    "dstOffset": 60,
                    "period": 300,
                    "startTime": 1752596100,
                    "timeZoneOffset": 60
                },
                {
                    "counterId": 30007,
                    "counterValue": 100.0,
                    "dnId": 118748818,
                    "dstOffset": 60,
                    "period": 300,
                    "startTime": 1752596400,
                    "timeZoneOffset": 60
                },
                {
                    "counterId": 30007,
                    "counterValue": 100.0,
                    "dnId": 118748818,
                    "dstOffset": 60,
                    "period": 300,
                    "startTime": 1752596700,
                    "timeZoneOffset": 60
                },
                {
                    "counterId": 30007,
                    "counterValue": 100.0,
                    "dnId": 118748818,
                    "dstOffset": 60,
                    "period": 300,
                    "startTime": 1752597000,
                    "timeZoneOffset": 60
                },
                {
                    "counterId": 30007,
                    "counterValue": 100.0,
                    "dnId": 118748818,
                    "dstOffset": 60,
                    "period": 300,
                    "startTime": 1752597300,
                    "timeZoneOffset": 60
                },
                {
                    "counterId": 30007,
                    "counterValue": 100.0,
                    "dnId": 118748818,
                    "dstOffset": 60,
                    "period": 300,
                    "startTime": 1752597600,
                    "timeZoneOffset": 60
                },
                {
                    "counterId": 30007,
                    "counterValue": 100.0,
                    "dnId": 118748818,
                    "dstOffset": 60,
                    "period": 300,
                    "startTime": 1752597900,
                    "timeZoneOffset": 60
                },
                {
                    "counterId": 30007,
                    "counterValue": 100.0,
                    "dnId": 118748818,
                    "dstOffset": 60,
                    "period": 300,
                    "startTime": 1752598200,
                    "timeZoneOffset": 60
                },
                {
                    "counterId": 30007,
                    "counterValue": 100.0,
                    "dnId": 118748818,
                    "dstOffset": 60,
                    "period": 300,
                    "startTime": 1752598500,
                    "timeZoneOffset": 60
                },
                {
                    "counterId": 30007,
                    "counterValue": 100.0,
                    "dnId": 118748818,
                    "dstOffset": 60,
                    "period": 300,
                    "startTime": 1752598800,
                    "timeZoneOffset": 60
                },
                {
                    "counterId": 30007,
                    "counterValue": 100.0,
                    "dnId": 118748818,
                    "dstOffset": 60,
                    "period": 300,
                    "startTime": 1752599100,
                    "timeZoneOffset": 60
                },
                {
                    "counterId": 30007,
                    "counterValue": 100.0,
                    "dnId": 118748818,
                    "dstOffset": 60,
                    "period": 300,
                    "startTime": 1752599400,
                    "timeZoneOffset": 60
                },
                {
                    "counterId": 30007,
                    "counterValue": 100.0,
                    "dnId": 118748818,
                    "dstOffset": 60,
                    "period": 300,
                    "startTime": 1752599700,
                    "timeZoneOffset": 60
                },
                {
                    "counterId": 30007,
                    "counterValue": 100.0,
                    "dnId": 118748818,
                    "dstOffset": 60,
                    "period": 300,
                    "startTime": 1752600000,
                    "timeZoneOffset": 60
                },
                {
                    "counterId": 30007,
                    "counterValue": 100.0,
                    "dnId": 118748818,
                    "dstOffset": 60,
                    "period": 300,
                    "startTime": 1752600300,
                    "timeZoneOffset": 60
                },
                {
                    "counterId": 30007,
                    "counterValue": 100.0,
                    "dnId": 118748818,
                    "dstOffset": 60,
                    "period": 300,
                    "startTime": 1752600600,
                    "timeZoneOffset": 60
                },
                {
                    "counterId": 30007,
                    "counterValue": 100.0,
                    "dnId": 118748818,
                    "dstOffset": 60,
                    "period": 300,
                    "startTime": 1752600900,
                    "timeZoneOffset": 60
                },
                {
                    "counterId": 30007,
                    "counterValue": 100.0,
                    "dnId": 118748818,
                    "dstOffset": 60,
                    "period": 300,
                    "startTime": 1752601200,
                    "timeZoneOffset": 60
                },
                {
                    "counterId": 30007,
                    "counterValue": 100.0,
                    "dnId": 118748818,
                    "dstOffset": 60,
                    "period": 300,
                    "startTime": 1752601500,
                    "timeZoneOffset": 60
                },
                {
                    "counterId": 30007,
                    "counterValue": 100.0,
                    "dnId": 118748818,
                    "dstOffset": 60,
                    "period": 300,
                    "startTime": 1752601800,
                    "timeZoneOffset": 60
                },
                {
                    "counterId": 30007,
                    "counterValue": 100.0,
                    "dnId": 118748818,
                    "dstOffset": 60,
                    "period": 300,
                    "startTime": 1752602100,
                    "timeZoneOffset": 60
                },
                {
                    "counterId": 30007,
                    "counterValue": 99.0,
                    "dnId": 118748818,
                    "dstOffset": 60,
                    "period": 300,
                    "startTime": 1752602400,
                    "timeZoneOffset": 60
                },
                {
                    "counterId": 30007,
                    "counterValue": 98.0,
                    "dnId": 118748818,
                    "dstOffset": 60,
                    "period": 300,
                    "startTime": 1752602700,
                    "timeZoneOffset": 60
                },
                {
                    "counterId": 30007,
                    "counterValue": 98.0,
                    "dnId": 118748818,
                    "dstOffset": 60,
                    "period": 300,
                    "startTime": 1752603000,
                    "timeZoneOffset": 60
                },
                {
                    "counterId": 30007,
                    "counterValue": 98.0,
                    "dnId": 118748818,
                    "dstOffset": 60,
                    "period": 300,
                    "startTime": 1752603300,
                    "timeZoneOffset": 60
                },
                {
                    "counterId": 30007,
                    "counterValue": 97.0,
                    "dnId": 118748818,
                    "dstOffset": 60,
                    "period": 300,
                    "startTime": 1752603600,
                    "timeZoneOffset": 60
                },
                {
                    "counterId": 30007,
                    "counterValue": 96.0,
                    "dnId": 118748818,
                    "dstOffset": 60,
                    "period": 300,
                    "startTime": 1752603900,
                    "timeZoneOffset": 60
                },
                {
                    "counterId": 30007,
                    "counterValue": 96.0,
                    "dnId": 118748818,
                    "dstOffset": 60,
                    "period": 300,
                    "startTime": 1752604200,
                    "timeZoneOffset": 60
                },
                {
                    "counterId": 30007,
                    "counterValue": 96.0,
                    "dnId": 118748818,
                    "dstOffset": 60,
                    "period": 300,
                    "startTime": 1752604500,
                    "timeZoneOffset": 60
                },
                {
                    "counterId": 30007,
                    "counterValue": 96.0,
                    "dnId": 118748818,
                    "dstOffset": 60,
                    "period": 300,
                    "startTime": 1752604800,
                    "timeZoneOffset": 60
                },
                {
                    "counterId": 30007,
                    "counterValue": 96.0,
                    "dnId": 118748818,
                    "dstOffset": 60,
                    "period": 300,
                    "startTime": 1752605100,
                    "timeZoneOffset": 60
                },
                {
                    "counterId": 30007,
                    "counterValue": 94.0,
                    "dnId": 118748818,
                    "dstOffset": 60,
                    "period": 300,
                    "startTime": 1752605400,
                    "timeZoneOffset": 60
                },
                {
                    "counterId": 30007,
                    "counterValue": 93.0,
                    "dnId": 118748818,
                    "dstOffset": 60,
                    "period": 300,
                    "startTime": 1752605700,
                    "timeZoneOffset": 60
                },
                {
                    "counterId": 30007,
                    "counterValue": 93.0,
                    "dnId": 118748818,
                    "dstOffset": 60,
                    "period": 300,
                    "startTime": 1752606000,
                    "timeZoneOffset": 60
                },
                {
                    "counterId": 30007,
                    "counterValue": 93.0,
                    "dnId": 118748818,
                    "dstOffset": 60,
                    "period": 300,
                    "startTime": 1752606300,
                    "timeZoneOffset": 60
                },
                {
                    "counterId": 30007,
                    "counterValue": 93.0,
                    "dnId": 118748818,
                    "dstOffset": 60,
                    "period": 300,
                    "startTime": 1752606600,
                    "timeZoneOffset": 60
                },
                {
                    "counterId": 30007,
                    "counterValue": 92.0,
                    "dnId": 118748818,
                    "dstOffset": 60,
                    "period": 300,
                    "startTime": 1752606900,
                    "timeZoneOffset": 60
                },
                {
                    "counterId": 30007,
                    "counterValue": 92.0,
                    "dnId": 118748818,
                    "dstOffset": 60,
                    "period": 300,
                    "startTime": 1752607200,
                    "timeZoneOffset": 60
                },
                {
                    "counterId": 30007,
                    "counterValue": 91.0,
                    "dnId": 118748818,
                    "dstOffset": 60,
                    "period": 300,
                    "startTime": 1752607500,
                    "timeZoneOffset": 60
                },
                {
                    "counterId": 30007,
                    "counterValue": 90.0,
                    "dnId": 118748818,
                    "dstOffset": 60,
                    "period": 300,
                    "startTime": 1752607800,
                    "timeZoneOffset": 60
                },
                {
                    "counterId": 30007,
                    "counterValue": 89.0,
                    "dnId": 118748818,
                    "dstOffset": 60,
                    "period": 300,
                    "startTime": 1752608100,
                    "timeZoneOffset": 60
                },
                {
                    "counterId": 30007,
                    "counterValue": 87.0,
                    "dnId": 118748818,
                    "dstOffset": 60,
                    "period": 300,
                    "startTime": 1752608400,
                    "timeZoneOffset": 60
                },
                {
                    "counterId": 30007,
                    "counterValue": 83.0,
                    "dnId": 118748818,
                    "dstOffset": 60,
                    "period": 300,
                    "startTime": 1752608700,
                    "timeZoneOffset": 60
                },
                {
                    "counterId": 30007,
                    "counterValue": 80.0,
                    "dnId": 118748818,
                    "dstOffset": 60,
                    "period": 300,
                    "startTime": 1752609000,
                    "timeZoneOffset": 60
                },
                {
                    "counterId": 30007,
                    "counterValue": 79.0,
                    "dnId": 118748818,
                    "dstOffset": 60,
                    "period": 300,
                    "startTime": 1752609300,
                    "timeZoneOffset": 60
                },
                {
                    "counterId": 30007,
                    "counterValue": 79.0,
                    "dnId": 118748818,
                    "dstOffset": 60,
                    "period": 300,
                    "startTime": 1752609600,
                    "timeZoneOffset": 60
                },
                {
                    "counterId": 30007,
                    "counterValue": 77.0,
                    "dnId": 118748818,
                    "dstOffset": 60,
                    "period": 300,
                    "startTime": 1752609900,
                    "timeZoneOffset": 60
                },
                {
                    "counterId": 30007,
                    "counterValue": 77.0,
                    "dnId": 118748818,
                    "dstOffset": 60,
                    "period": 300,
                    "startTime": 1752610200,
                    "timeZoneOffset": 60
                },
                {
                    "counterId": 30007,
                    "counterValue": 76.0,
                    "dnId": 118748818,
                    "dstOffset": 60,
                    "period": 300,
                    "startTime": 1752610500,
                    "timeZoneOffset": 60
                },
                {
                    "counterId": 30007,
                    "counterValue": 76.0,
                    "dnId": 118748818,
                    "dstOffset": 60,
                    "period": 300,
                    "startTime": 1752610800,
                    "timeZoneOffset": 60
                },
                {
                    "counterId": 30007,
                    "counterValue": 75.0,
                    "dnId": 118748818,
                    "dstOffset": 60,
                    "period": 300,
                    "startTime": 1752611100,
                    "timeZoneOffset": 60
                },
                {
                    "counterId": 30007,
                    "counterValue": 74.0,
                    "dnId": 118748818,
                    "dstOffset": 60,
                    "period": 300,
                    "startTime": 1752611400,
                    "timeZoneOffset": 60
                },
                {
                    "counterId": 30007,
                    "counterValue": 74.0,
                    "dnId": 118748818,
                    "dstOffset": 60,
                    "period": 300,
                    "startTime": 1752611700,
                    "timeZoneOffset": 60
                },
                {
                    "counterId": 30007,
                    "counterValue": 74.0,
                    "dnId": 118748818,
                    "dstOffset": 60,
                    "period": 300,
                    "startTime": 1752612000,
                    "timeZoneOffset": 60
                },
                {
                    "counterId": 30007,
                    "counterValue": 74.0,
                    "dnId": 118748818,
                    "dstOffset": 60,
                    "period": 300,
                    "startTime": 1752612300,
                    "timeZoneOffset": 60
                },
                {
                    "counterId": 30007,
                    "counterValue": 73.0,
                    "dnId": 118748818,
                    "dstOffset": 60,
                    "period": 300,
                    "startTime": 1752612600,
                    "timeZoneOffset": 60
                },
                {
                    "counterId": 30007,
                    "counterValue": 73.0,
                    "dnId": 118748818,
                    "dstOffset": 60,
                    "period": 300,
                    "startTime": 1752612900,
                    "timeZoneOffset": 60
                },
                {
                    "counterId": 30007,
                    "counterValue": 73.0,
                    "dnId": 118748818,
                    "dstOffset": 60,
                    "period": 300,
                    "startTime": 1752613200,
                    "timeZoneOffset": 60
                },
                {
                    "counterId": 30007,
                    "counterValue": 73.0,
                    "dnId": 118748818,
                    "dstOffset": 60,
                    "period": 300,
                    "startTime": 1752613500,
                    "timeZoneOffset": 60
                },
                {
                    "counterId": 30007,
                    "counterValue": 73.0,
                    "dnId": 118748818,
                    "dstOffset": 60,
                    "period": 300,
                    "startTime": 1752613800,
                    "timeZoneOffset": 60
                },
                {
                    "counterId": 30007,
                    "counterValue": 72.0,
                    "dnId": 118748818,
                    "dstOffset": 60,
                    "period": 300,
                    "startTime": 1752614100,
                    "timeZoneOffset": 60
                },
                {
                    "counterId": 30007,
                    "counterValue": 72.0,
                    "dnId": 118748818,
                    "dstOffset": 60,
                    "period": 300,
                    "startTime": 1752614400,
                    "timeZoneOffset": 60
                },
                {
                    "counterId": 30007,
                    "counterValue": 72.0,
                    "dnId": 118748818,
                    "dstOffset": 60,
                    "period": 300,
                    "startTime": 1752614700,
                    "timeZoneOffset": 60
                },
                {
                    "counterId": 30007,
                    "counterValue": 72.0,
                    "dnId": 118748818,
                    "dstOffset": 60,
                    "period": 300,
                    "startTime": 1752615000,
                    "timeZoneOffset": 60
                },
                {
                    "counterId": 30007,
                    "counterValue": 72.0,
                    "dnId": 118748818,
                    "dstOffset": 60,
                    "period": 300,
                    "startTime": 1752615300,
                    "timeZoneOffset": 60
                },
                {
                    "counterId": 30007,
                    "counterValue": 71.0,
                    "dnId": 118748818,
                    "dstOffset": 60,
                    "period": 300,
                    "startTime": 1752615600,
                    "timeZoneOffset": 60
                },
                {
                    "counterId": 30007,
                    "counterValue": 71.0,
                    "dnId": 118748818,
                    "dstOffset": 60,
                    "period": 300,
                    "startTime": 1752615900,
                    "timeZoneOffset": 60
                },
                {
                    "counterId": 30007,
                    "counterValue": 71.0,
                    "dnId": 118748818,
                    "dstOffset": 60,
                    "period": 300,
                    "startTime": 1752616200,
                    "timeZoneOffset": 60
                },
                {
                    "counterId": 30007,
                    "counterValue": 71.0,
                    "dnId": 118748818,
                    "dstOffset": 60,
                    "period": 300,
                    "startTime": 1752616500,
                    "timeZoneOffset": 60
                }
            ],
            "total": 288
        }
    },
    "failCode": 0,
    "params": [],
    "success": true
}