{
    "buildCode": "2",
    "data": {
        "30007": {
            "pmDataList": [
                {
                    "counterId": 30007,
                    "counterValue": 5.0,
                    "dnId": 118748818,
                    "dstOffset": 0,
                    "period": 300,
                    "startTime": 1766098800,
                    "timeZoneOffset": 60
                },
                {
                    "counterId": 30007,
                    "counterValue": 5.0,
                    "dnId": 118748818,
                    "dstOffset": 0,
                    "period": 300,
                    "startTime": 1766099100,
                    "timeZoneOffset": 60
                },
                {
                    "counterId": 30007,
                    "counterValue": 5.0,
                    "dnId": 118748818,
                    "dstOffset": 0,
                    "period": 300,
                    "startTime": 1766099400,
                    "timeZoneOffset": 60
                },
                {
                    "counterId": 30007,
                    "counterValue": 5.0,
                    "dnId": 118748818,
                    "dstOffset": 0,
                    "period": 300,
                    "startTime": 1766099700,
                    "timeZoneOffset": 60
                },
                {
                    "counterId": 30007,
                    "counterValue": 5.0,
                    "dnId": 118748818,
                    "dstOffset": 0,
                    "period": 300,
                    "startTime": 1766100000,
                    "timeZoneOffset": 60
                },
                {
                    "counterId": 30007,
                    "counterValue": 5.0,
                    "dnId": 118748818,
                    "dstOffset": 0,
                    "period": 300,
                    "startTime": 1766100300,
                    "timeZoneOffset": 60
                },
                {
                    "counterId": 30007,
                    "counterValue": 5.0,
                    "dnId": 118748818,
                    "dstOffset": 0,
                    "period": 300,
                    "startTime": 1766100600,
                    "timeZoneOffset": 60
                },
                {
                    "counterId": 30007,
                    "counterValue": 5.0,
                    "dnId": 118748818,
                    "dstOffset": 0,
                    "period": 300,
                    "startTime": 1766100900,
                    "timeZoneOffset": 60
                },
                {
                    "counterId": 30007,
                    "counterValue": 5.0,
                    "dnId": 118748818,
                    "dstOffset": 0,
                    "period": 300,
                    "startTime": 1766101200,
                    "timeZoneOffset": 60
                },
                {
                    "counterId": 30007,
                    "counterValue": 5.0,
                    "dnId": 118748818,
                    "dstOffset": 0,
                    "period": 300,
                    "startTime": 1766101500,
                    "timeZoneOffset": 60
                },
                {
                    "counterId": 30007,
                    "counterValue": 5.0,
                    "dnId": 118748818,
                    "dstOffset": 0,
                    "period": 300,
                    "startTime": 1766101800,
                    "timeZoneOffset": 60
                },
                {
                    "counterId": 30007,
                    "counterValue": 5.0,
                    "dnId": 118748818,
                    "dstOffset": 0,
                    "period": 300,
                    "startTime": 1766102100,
                    "timeZoneOffset": 60
                },
                {
                    "counterId": 30007,
                    "counterValue": 5.0,
                    "dnId": 118748818,
                    "dstOffset": 0,
                    "period": 300,
                    "startTime": 1766102400,
                    "timeZoneOffset": 60
                },
                {
                    "counterId": 30007,
                    "counterValue": 5.0,
                    "dnId": 118748818,
                    "dstOffset": 0,
                    "period": 300,
                    "startTime": 1766102700,
                    "timeZoneOffset": 60
                },
                {
                    "counterId": 30007,
                    "counterValue": 5.0,
                    "dnId": 118748818,
                    "dstOffset": 0,
                    "period": 300,
                    "startTime": 1766103000,
                    "timeZoneOffset": 60
                },
                {
                    "counterId": 30007,
                    "counterValue": 5.0,
                    "dnId": 118748818,
                    "dstOffset": 0,
                    "period": 300,
                    "startTime": 1766103300,
                    "timeZoneOffset": 60
                },
                {
                    "counterId": 30007,
                    "counterValue": 5.0,
                    "dnId": 118748818,
                    "dstOffset": 0,
                    "period": 300,
                    "startTime": 1766103600,
                    "timeZoneOffset": 60
                },
                {
                    "counterId": 30007,
                    "counterValue": 5.0,
                    "dnId": 118748818,
                    "dstOffset": 0,
                    "period": 300,
                    "startTime": 1766103900,
                    "timeZoneOffset": 60
                },
                {
                    "counterId": 30007,
                    "counterValue": 5.0,
                    "dnId": 118748818,
                    "dstOffset": 0,
                    "period": 300,
                    "startTime": 1766104200,
                    "timeZoneOffset": 60
                },
                {
                    "counterId": 30007,
                    "counterValue": 5.0,
                    "dnId": 118748818,
                    "dstOffset": 0,
                    "period": 300,
                    "startTime": 1766104500,
                    "timeZoneOffset": 60
                },
                {
                    "counterId": 30007,
                    "counterValue": 5.0,
                    "dnId": 118748818,
                    "dstOffset": 0,
                    "period": 300,
                    "startTime": 1766104800,
                    "timeZoneOffset": 60
                },
                {
                    "counterId": 30007,
                    "counterValue": 5.0,
                    "dnId": 118748818,
                    "dstOffset": 0,
                    "period": 300,
                    "startTime": 1766105100,
                    "timeZoneOffset": 60
                },
                {
                    "counterId": 30007,
                    "counterValue": 5.0,
                    "dnId": 118748818,
                    "dstOffset": 0,
                    "period": 300,
                    "startTime": 1766105400,
                    "timeZoneOffset": 60
                },
                {
                    "counterId": 30007,
                    "counterValue": 5.0,
                    "dnId": 118748818,
                    "dstOffset": 0,
                    "period": 300,
                    "startTime": 1766105700,
                    "timeZoneOffset": 60
                },
                {
                    "counterId": 30007,
                    "counterValue": 5.0,
                    "dnId": 118748818,
                    "dstOffset": 0,
                    "period": 300,
                    "startTime": 1766106000,
                    "timeZoneOffset": 60
                },
                {
                    "counterId": 30007,
                    "counterValue": 5.0,
                    "dnId": 118748818,
                    "dstOffset": 0,
                    "period": 300,
                    "startTime": 1766106300,
                    "timeZoneOffset": 60
                },
                {
                    "counterId": 30007,
                    "counterValue": 5.0,
                    "dnId": 118748818,
                    "dstOffset": 0,
                    "period": 300,
                    "startTime": 1766106600,
                    "timeZoneOffset": 60
                },
                {
                    "counterId": 30007,
                    "counterValue": 5.0,
                    "dnId": 118748818,
                    "dstOffset": 0,
                    "period": 300,
                    "startTime": 1766106900,
                    "timeZoneOffset": 60
                },
                {
                    "counterId": 30007,
                    "counterValue": 5.0,
                    "dnId": 118748818,
                    "dstOffset": 0,
                    "period": 300,
                    "startTime": 1766107200,
                    "timeZoneOffset": 60
                },
                {
                    "counterId": 30007,
                    "counterValue": 5.0,
                    "dnId": 118748818,
                    "dstOffset": 0,
                    "period": 300,
                    "startTime": 1766107500,
                    "timeZoneOffset": 60
                },
                {
                    "counterId": 30007,
                    "counterValue": 5.0,
                    "dnId": 118748818,
                    "dstOffset": 0,
                    "period": 300,
                    "startTime": 1766107800,
                    "timeZoneOffset": 60
                },
                {
                    "counterId": 30007,
                    "counterValue": 5.0,
                    "dnId": 118748818,
                    "dstOffset": 0,
                    "period": 300,
                    "startTime": 1766108100,
                    "timeZoneOffset": 60
                },
                {
                    "counterId": 30007,
                    "counterValue": 5.0,
                    "dnId": 118748818,
                    "dstOffset": 0,
                    "period": 300,
                    "startTime": 1766108400,
                    "timeZoneOffset": 60
                },
                {
                    "counterId": 30007,
                    "counterValue": 5.0,
                    "dnId": 118748818,
                    "dstOffset": 0,
                    "period": 300,
                    "startTime": 1766108700,
                    "timeZoneOffset": 60
                },
                {
                    "counterId": 30007,
                    "counterValue": 5.0,
                    "dnId": 118748818,
                    "dstOffset": 0,
                    "period": 300,
                    "startTime": 1766109000,
                    "timeZoneOffset": 60
                },
                {
                    "counterId": 30007,
                    "counterValue": 5.0,
                    "dnId": 118748818,
                    "dstOffset": 0,
                    "period": 300,
                    "startTime": 1766109300,
                    "timeZoneOffset": 60
                },
                {
                    "counterId": 30007,
                    "counterValue": 5.0,
                    "dnId": 118748818,
                    "dstOffset": 0,
                    "period": 300,
                    "startTime": 1766109600,
                    "timeZoneOffset": 60
                },
                {
                    "counterId": 30007,
                    "counterValue": 5.0,
                    "dnId": 118748818,
                    "dstOffset": 0,
                    "period": 300,
                    "startTime": 1766109900,
                    "timeZoneOffset": 60
                },
                {
                    "counterId": 30007,
                    "counterValue": 5.0,
                    "dnId": 118748818,
                    "dstOffset": 0,
                    "period": 300,
                    "startTime": 1766110200,
                    "timeZoneOffset": 60
                },
                {
                    "counterId": 30007,
                    "counterValue": 5.0,
                    "dnId": 118748818,
                    "dstOffset": 0,
                    "period": 300,
                    "startTime": 1766110500,
                    "timeZoneOffset": 60
                },
                {
                    "counterId": 30007,
                    "counterValue": 5.0,
                    "dnId": 118748818,
                    "dstOffset": 0,
                    "period": 300,
                    "startTime": 1766110800,
                    "timeZoneOffset": 60
                },
                {
                    "counterId": 30007,
                    "counterValue": 5.0,
                    "dnId": 118748818,
                    "dstOffset": 0,
                    "period": 300,
                    "startTime": 1766111100,
                    "timeZoneOffset": 60
                },
                {
                    "counterId": 30007,
                    "counterValue": 5.0,
                    "dnId": 118748818,
                    "dstOffset": 0,
                    "period": 300,
                    "startTime": 1766111400,
                    "timeZoneOffset": 60
                },
                {
                    "counterId": 30007,
                    "counterValue": 5.0,
                    "dnId": 118748818,
                    "dstOffset": 0,
                    "period": 300,
                    "startTime": 1766111700,
                    "timeZoneOffset": 60
                },
                {
                    "counterId": 30007,
                    "counterValue": 5.0,
                    "dnId": 118748818,
                    "dstOffset": 0,
                    "period": 300,
                    "startTime": 1766112000,
                    "timeZoneOffset": 60
                },
                {
                    "counterId": 30007,
                    "counterValue": 5.0,
                    "dnId": 118748818,
                    "dstOffset": 0,
                    "period": 300,
                    "startTime": 1766112300,
                    "timeZoneOffset": 60
                },
                {
                    "counterId": 30007,
                    "counterValue": 5.0,
                    "dnId": 118748818,
                    "dstOffset": 0,
                    "period": 300,
                    "startTime": 1766112600,
                    "timeZoneOffset": 60
                },
                {
                    "counterId": 30007,
                    "counterValue": 5.0,
                    "dnId": 118748818,
                    "dstOffset": 0,
                    "period": 300,
                    "startTime": 1766112900,
                    "timeZoneOffset": 60
                },
                {
                    "counterId": 30007,
                    "counterValue": 5.0,
                    "dnId": 118748818,
                    "dstOffset": 0,
                    "period": 300,
                    "startTime": 1766113200,
                    "timeZoneOffset": 60
                },
                {
                    "counterId": 30007,
                    "counterValue": 5.0,
                    "dnId": 118748818,
                    "dstOffset": 0,
                    "period": 300,
                    "startTime": 1766113500,
                    "timeZoneOffset": 60
                },
                {
                    "counterId": 30007,
                    "counterValue": 5.0,
                    "dnId": 118748818,
                    "dstOffset": 0,
                    "period": 300,
                    "startTime": 1766113800,
                    "timeZoneOffset": 60
                },
                {
                    "counterId": 30007,
                    "counterValue": 5.0,
                    "dnId": 118748818,
                    "dstOffset": 0,
                    "period": 300,
                    "startTime": 1766114100,
                    "timeZoneOffset": 60
                },
                {
                    "counterId": 30007,
                    "counterValue": 5.0,
                    "dnId": 118748818,
                    "dstOffset": 0,
                    "period": 300,
                    "startTime": 1766114400,
                    "timeZoneOffset": 60
                },
                {
                    "counterId": 30007,
                    "counterValue": 5.0,
                    "dnId": 118748818,
                    "dstOffset": 0,
                    "period": 300,
                    "startTime": 1766114700,
                    "timeZoneOffset": 60
                },
                {
                    "counterId": 30007,
                    "counterValue": 5.0,
                    "dnId": 118748818,
                    "dstOffset": 0,
                    "period": 300,
                    "startTime": 1766115000,
                    "timeZoneOffset": 60
                },
                {
                    "counterId": 30007,
                    "counterValue": 5.0,
                    "dnId": 118748818,
                    "dstOffset": 0,
                    "period": 300,
                    "startTime": 1766115300,
                    "timeZoneOffset": 60
                },
                {
                    "counterId": 30007,
                    "counterValue": 5.0,
                    "dnId": 118748818,
                    "dstOffset": 0,
                    "period": 300,
                    "startTime": 1766115600,
                    "timeZoneOffset": 60
                },
                {
                    "counterId": 30007,
                    "counterValue": 5.0,
                    "dnId": 118748818,
                    "dstOffset": 0,
                    "period": 300,
                    "startTime": 1766115900,
                    "timeZoneOffset": 60
                },
                {
                    "counterId": 30007,
                    "counterValue": 5.0,
                    "dnId": 118748818,
                    "dstOffset": 0,
                    "period": 300,
                    "startTime": 1766116200,
                    "timeZoneOffset": 60
                },
                {
                    "counterId": 30007,
                    "counterValue": 5.0,
                    "dnId": 118748818,
                    "dstOffset": 0,
                    "period": 300,
                    "startTime": 1766116500,
                    "timeZoneOffset": 60
                },
                {
                    "counterId": 30007,
                    "counterValue": 5.0,
                    "dnId": 118748818,
                    "dstOffset": 0,
                    "period": 300,
                    "startTime": 1766116800,
                    "timeZoneOffset": 60
                },
                {
                    "counterId": 30007,
                    "counterValue": 5.0,
                    "dnId": 118748818,
                    "dstOffset": 0,
                    "period": 300,
                    "startTime": 1766117100,
                    "timeZoneOffset": 60
                },
                {
                    "counterId": 30007,
                    "counterValue": 5.0,
                    "dnId": 118748818,
                    "dstOffset": 0,
                    "period": 300,
                    "startTime": 1766117400,
                    "timeZoneOffset": 60
                },
                {
                    "counterId": 30007,
                    "counterValue": 5.0,
                    "dnId": 118748818,
                    "dstOffset": 0,
                    "period": 300,
                    "startTime": 1766117700,
                    "timeZoneOffset": 60
                },
                {
                    "counterId": 30007,
                    "counterValue": 5.0,
                    "dnId": 118748818,
                    "dstOffset": 0,
                    "period": 300,
                    "startTime": 1766118000,
                    "timeZoneOffset": 60
                },
                {
                    "counterId": 30007,
                    "counterValue": 5.0,
                    "dnId": 118748818,
                    "dstOffset": 0,
                    "period": 300,
                    "startTime": 1766118300,
                    "timeZoneOffset": 60
                },
                {
                    "counterId": 30007,
                    "counterValue": 5.0,
                    "dnId": 118748818,
                    "dstOffset": 0,
                    "period": 300,
                    "startTime": 1766118600,
                    "timeZoneOffset": 60
                },
                {
                    "counterId": 30007,
                    "counterValue": 5.0,
                    "dnId": 118748818,
                    "dstOffset": 0,
                    "period": 300,
                    "startTime": 1766118900,
                    "timeZoneOffset": 60
                },
                {
                    "counterId": 30007,
                    "counterValue": 5.0,
                    "dnId": 118748818,
                    "dstOffset": 0,
                    "period": 300,
                    "startTime": 1766119200,
                    "timeZoneOffset": 60
                },
                {
                    "counterId": 30007,
                    "counterValue": 5.0,
                    "dnId": 118748818,
                    "dstOffset": 0,
                    "period": 300,
                    "startTime": 1766119500,
                    "timeZoneOffset": 60
                },
                {
                    "counterId": 30007,
                    "counterValue": 5.0,
                    "dnId": 118748818,
                    "dstOffset": 0,
                    "period": 300,
                    "startTime": 1766119800,
                    "timeZoneOffset": 60
                },
                {
                    "counterId": 30007,
                    "counterValue": 5.0,
                    "dnId": 118748818,
                    "dstOffset": 0,
                    "period": 300,
                    "startTime": 1766120100,
                    "timeZoneOffset": 60
                },
                {
                    "counterId": 30007,
                    "counterValue": 5.0,
                    "dnId": 118748818,
                    "dstOffset": 0,
                    "period": 300,
                    "startTime": 1766120400,
                    "timeZoneOffset": 60
                },
                {
                    "counterId": 30007,
                    "counterValue": 5.0,
                    "dnId": 118748818,
                    "dstOffset": 0,
                    "period": 300,
                    "startTime": 1766120700,
                    "timeZoneOffset": 60
                },
                {
                    "counterId": 30007,
                    "counterValue": 5.0,
                    "dnId": 118748818,
                    "dstOffset": 0,
                    "period": 300,
                    "startTime": 1766121000,
                    "timeZoneOffset": 60
                },
                {
                    "counterId": 30007,
                    "counterValue": 5.0,
                    "dnId": 118748818,
                    "dstOffset": 0,
                    "period": 300,
                    "startTime": 1766121300,
                    "timeZoneOffset": 60
                },
                {
                    "counterId": 30007,
                    "counterValue": 5.0,
                    "dnId": 118748818,
                    "dstOffset": 0,
                    "period": 300,
                    "startTime": 1766121600,
                    "timeZoneOffset": 60
                },
                {
                    "counterId": 30007,
                    "counterValue": 5.0,
                    "dnId": 118748818,
                    "dstOffset": 0,
                    "period": 300,
                    "startTime": 1766121900,
                    "timeZoneOffset": 60
                },
                {
                    "counterId": 30007,
                    "counterValue": 5.0,
                    "dnId": 118748818,
                    "dstOffset": 0,
                    "period": 300,
                    "startTime": 1766122200,
                    "timeZoneOffset": 60
                },
                {
                    "counterId": 30007,
                    "counterValue": 5.0,
                    "dnId": 118748818,
                    "dstOffset": 0,
                    "period": 300,
                    "startTime": 1766122500,
                    "timeZoneOffset": 60
                },
                {
                    "counterId": 30007,
                    "counterValue": 5.0,
                    "dnId": 118748818,
                    "dstOffset": 0,
                    "period": 300,
                    "startTime": 1766122800,
                    "timeZoneOffset": 60
                },
                {
                    "counterId": 30007,
                    "counterValue": 5.0,
                    "dnId": 118748818,
                    "dstOffset": 0,
                    "period": 300,
                    "startTime": 1766123100,
                    "timeZoneOffset": 60
                },
                {
                    "counterId": 30007,
                    "counterValue": 5.0,
                    "dnId": 118748818,
                    "dstOffset": 0,
                    "period": 300,
                    "startTime": 1766123400,
                    "timeZoneOffset": 60
                },
                {
                    "counterId": 30007,
                    "counterValue": 5.0,
                    "dnId": 118748818,
                    "dstOffset": 0,
                    "period": 300,
                    "startTime": 1766123700,
                    "timeZoneOffset": 60
                },
                {
                    "counterId": 30007,
                    "counterValue": 5.0,
                    "dnId": 118748818,
                    "dstOffset": 0,
                    "period": 300,
                    "startTime": 1766124000,
                    "timeZoneOffset": 60
                },
                {
                    "counterId": 30007,
                    "counterValue": 5.0,
                    "dnId": 118748818,
                    "dstOffset": 0,
                    "period": 300,
                    "startTime": 1766124300,
                    "timeZoneOffset": 60
                },
                {
                    "counterId": 30007,
                    "counterValue": 5.0,
                    "dnId": 118748818,
                    "dstOffset": 0,
                    "period": 300,
                    "startTime": 1766124600,
                    "timeZoneOffset": 60
                },
                {
                    "counterId": 30007,
                    "counterValue": 5.0,
                    "dnId": 118748818,
                    "dstOffset": 0,
                    "period": 300,
                    "startTime": 1766124900,
                    "timeZoneOffset": 60
                },
                {
                    "counterId": 30007,
                    "counterValue": 5.0,
                    "dnId": 118748818,
                    "dstOffset": 0,
                    "period": 300,
                    "startTime": 1766125200,
                    "timeZoneOffset": 60
                },
                {
                    "counterId": 30007,
                    "counterValue": 5.0,
                    "dnId": 118748818,
                    "dstOffset": 0,
                    "period": 300,
                    "startTime": 1766125500,
                    "timeZoneOffset": 60
                },
                {
                    "counterId": 30007,
                    "counterValue": 5.0,
                    "dnId": 118748818,
                    "dstOffset": 0,
                    "period": 300,
                    "startTime": 1766125800,
                    "timeZoneOffset": 60
                },
                {
                    "counterId": 30007,
                    "counterValue": 5.0,
                    "dnId": 118748818,
                    "dstOffset": 0,
                    "period": 300,
                    "startTime": 1766126100,
                    "timeZoneOffset": 60
                },
                {
                    "counterId": 30007,
                    "counterValue": 5.0,
                    "dnId": 118748818,
                    "dstOffset": 0,
                    "period": 300,
                    "startTime": 1766126400,
                    "timeZoneOffset": 60
                },
                {
                    "counterId": 30007,
                    "counterValue": 5.0,
                    "dnId": 118748818,
                    "dstOffset": 0,
                    "period": 300,
                    "startTime": 1766126700,
                    "timeZoneOffset": 60
                },
                {
                    "counterId": 30007,
                    "counterValue": 5.0,
                    "dnId": 118748818,
                    "dstOffset": 0,
                    "period": 300,
                    "startTime": 1766127000,
                    "timeZoneOffset": 60
                },
                {
                    "counterId": 30007,
                    "counterValue": 5.0,
                    "dnId": 118748818,
                    "dstOffset": 0,
                    "period": 300,
                    "startTime": 1766127300,
                    "timeZoneOffset": 60
                },
                {
                    "counterId": 30007,
                    "counterValue": 5.0,
                    "dnId": 118748818,
                    "dstOffset": 0,
                    "period": 300,
                    "startTime": 1766127600,
                    "timeZoneOffset": 60
                },
                {
                    "counterId": 30007,
                    "counterValue": 5.0,
                    "dnId": 118748818,
                    "dstOffset": 0,
                    "period": 300,
                    "startTime": 1766127900,
                    "timeZoneOffset": 60
                },
                {
                    "counterId": 30007,
                    "counterValue": 5.0,
                    "dnId": 118748818,
                    "dstOffset": 0,
                    "period": 300,
                    "startTime": 1766128200,
                    "timeZoneOffset": 60
                },
                {
                    "counterId": 30007,
                    "counterValue": 5.0,
                    "dnId": 118748818,
                    "dstOffset": 0,
                    "period": 300,
                    "startTime": 1766128500,
                    "timeZoneOffset": 60
                },
                {
                    "counterId": 30007,
                    "counterValue": 5.0,
                    "dnId": 118748818,
                    "dstOffset": 0,
                    "period": 300,
                    "startTime": 1766128800,
                    "timeZoneOffset": 60
                },
                {
                    "counterId": 30007,
                    "counterValue": 5.0,
                    "dnId": 118748818,
                    "dstOffset": 0,
                    "period": 300,
                    "startTime": 1766129100,
                    "timeZoneOffset": 60
                },
                {
                    "counterId": 30007,
                    "counterValue": 5.0,
                    "dnId": 118748818,
                    "dstOffset": 0,
                    "period": 300,
                    "startTime": 1766129400,
                    "timeZoneOffset": 60
                },
                {
                    "counterId": 30007,
                    "counterValue": 5.0,
                    "dnId": 118748818,
                    "dstOffset": 0,
                    "period": 300,
                    "startTime": 1766129700,
                    "timeZoneOffset": 60
                },
                {
                    "counterId": 30007,
                    "counterValue": 5.0,
                    "dnId": 118748818,
                    "dstOffset": 0,
                    "period": 300,
                    "startTime": 1766130000,
                    "timeZoneOffset": 60
                },
                {
                    "counterId": 30007,
                    "counterValue": 5.0,
                    "dnId": 118748818,
                    "dstOffset": 0,
                    "period": 300,
                    "startTime": 1766130300,
                    "timeZoneOffset": 60
                },
                {
                    "counterId": 30007,
                    "counterValue": 5.0,
                    "dnId": 118748818,
                    "dstOffset": 0,
                    "period": 300,
                    "startTime": 1766130600,
                    "timeZoneOffset": 60
                },
                {
                    "counterId": 30007,
                    "counterValue": 5.0,
                    "dnId": 118748818,
                    "dstOffset": 0,
                    "period": 300,
                    "startTime": 1766130900,
                    "timeZoneOffset": 60
                },
                {
                    "counterId": 30007,
                    "counterValue": 5.0,
                    "dnId": 118748818,
                    "dstOffset": 0,
                    "period": 300,
                    "startTime": 1766131200,
                    "timeZoneOffset": 60
                },
                {
                    "counterId": 30007,
                    "counterValue": 5.0,
                    "dnId": 118748818,
                    "dstOffset": 0,
                    "period": 300,
                    "startTime": 1766131500,
                    "timeZoneOffset": 60
                },
                {
                    "counterId": 30007,
                    "counterValue": 5.0,
                    "dnId": 118748818,
                    "dstOffset": 0,
                    "period": 300,
                    "startTime": 1766131800,
                    "timeZoneOffset": 60
                },
                {
                    "counterId": 30007,
                    "counterValue": 5.0,
                    "dnId": 118748818,
                    "dstOffset": 0,
                    "period": 300,
                    "startTime": 1766132100,
                    "timeZoneOffset": 60
                },
                {
                    "counterId": 30007,
                    "counterValue": 5.0,
                    "dnId": 118748818,
                    "dstOffset": 0,
                    "period": 300,
                    "startTime": 1766132400,
                    "timeZoneOffset": 60
                },
                {
                    "counterId": 30007,
                    "counterValue": 5.0,
                    "dnId": 118748818,
                    "dstOffset": 0,
                    "period": 300,
                    "startTime": 1766132700,
                    "timeZoneOffset": 60
                },
                {
                    "counterId": 30007,
                    "counterValue": 5.0,
                    "dnId": 118748818,
                    "dstOffset": 0,
                    "period": 300,
                    "startTime": 1766133000,
                    "timeZoneOffset": 60
                },
                {
                    "counterId": 30007,
                    "counterValue": 5.0,
                    "dnId": 118748818,
                    "dstOffset": 0,
                    "period": 300,
                    "startTime": 1766133300,
                    "timeZoneOffset": 60
                },
                {
                    "counterId": 30007,
                    "counterValue": 5.0,
                    "dnId": 118748818,
                    "dstOffset": 0,
                    "period": 300,
                    "startTime": 1766133600,
                    "timeZoneOffset": 60
                },
                {
                    "counterId": 30007,
                    "counterValue": 5.0,
                    "dnId": 118748818,
                    "dstOffset": 0,
                    "period": 300,
                    "startTime": 1766133900,
                    "timeZoneOffset": 60
                },
                {
                    "counterId": 30007,
                    "counterValue": 5.0,
                    "dnId": 118748818,
                    "dstOffset": 0,
                    "period": 300,
                    "startTime": 1766134200,
                    "timeZoneOffset": 60
                },
                {
                    "counterId": 30007,
                    "counterValue": 5.0,
                    "dnId": 118748818,
                    "dstOffset": 0,
                    "period": 300,
                    "startTime": 1766134500,
                    "timeZoneOffset": 60
                },
                {
                    "counterId": 30007,
                    "counterValue": 5.0,
                    "dnId": 118748818,
                    "dstOffset": 0,
                    "period": 300,
                    "startTime": 1766134800,
                    "timeZoneOffset": 60
                },
                {
                    "counterId": 30007,
                    "counterValue": 5.0,
                    "dnId": 118748818,
                    "dstOffset": 0,
                    "period": 300,
                    "startTime": 1766135100,
                    "timeZoneOffset": 60
                },
                {
                    "counterId": 30007,
                    "counterValue": 5.0,
                    "dnId": 118748818,
                    "dstOffset": 0,
                    "period": 300,
                    "startTime": 1766135400,
                    "timeZoneOffset": 60
                },
                {
                    "counterId": 30007,
                    "counterValue": 5.0,
                    "dnId": 118748818,
                    "dstOffset": 0,
                    "period": 300,
                    "startTime": 1766135700,
                    "timeZoneOffset": 60
                },
                {
                    "counterId": 30007,
                    "counterValue": 5.0,
                    "dnId": 118748818,
                    "dstOffset": 0,
                    "period": 300,
                    "startTime": 1766136000,
                    "timeZoneOffset": 60
                },
                {
                    "counterId": 30007,
                    "counterValue": 5.0,
                    "dnId": 118748818,
                    "dstOffset": 0,
                    "period": 300,
                    "startTime": 1766136300,
                    "timeZoneOffset": 60
                },
                {
                    "counterId": 30007,
                    "counterValue": 5.0,
                    "dnId": 118748818,
                    "dstOffset": 0,
                    "period": 300,
                    "startTime": 1766136600,
                    "timeZoneOffset": 60
                },
                {
                    "counterId": 30007,
                    "counterValue": 5.0,
                    "dnId": 118748818,
                    "dstOffset": 0,
                    "period": 300,
                    "startTime": 1766136900,
                    "timeZoneOffset": 60
                },
                {
                    "counterId": 30007,
                    "counterValue": 5.0,
                    "dnId": 118748818,
                    "dstOffset": 0,
                    "period": 300,
                    "startTime": 1766137200,
                    "timeZoneOffset": 60
                },
                {
                    "counterId": 30007,
                    "counterValue": 5.0,
                    "dnId": 118748818,
                    "dstOffset": 0,
                    "period": 300,
                    "startTime": 1766137500,
                    "timeZoneOffset": 60
                },
                {
                    "counterId": 30007,
                    "counterValue": 5.0,
                    "dnId": 118748818,
                    "dstOffset": 0,
                    "period": 300,
                    "startTime": 1766137800,
                    "timeZoneOffset": 60
                },
                {
                    "counterId": 30007,
                    "counterValue": 5.0,
                    "dnId": 118748818,
                    "dstOffset": 0,
                    "period": 300,
                    "startTime": 1766138100,
                    "timeZoneOffset": 60
                },
                {
                    "counterId": 30007,
                    "counterValue": 5.0,
                    "dnId": 118748818,
                    "dstOffset": 0,
                    "period": 300,
                    "startTime": 1766138400,
                    "timeZoneOffset": 60
                },
                {
                    "counterId": 30007,
                    "counterValue": 5.0,
                    "dnId": 118748818,
                    "dstOffset": 0,
                    "period": 300,
                    "startTime": 1766138700,
                    "timeZoneOffset": 60
                },
                {
                    "counterId": 30007,
                    "counterValue": 5.0,
                    "dnId": 118748818,
                    "dstOffset": 0,
                    "period": 300,
                    "startTime": 1766139000,
                    "timeZoneOffset": 60
                },
                {
                    "counterId": 30007,
                    "counterValue": 5.0,
                    "dnId": 118748818,
                    "dstOffset": 0,
                    "period": 300,
                    "startTime": 1766139300,
                    "timeZoneOffset": 60
                },
                {
                    "counterId": 30007,
                    "counterValue": 5.0,
                    "dnId": 118748818,
                    "dstOffset": 0,
                    "period": 300,
                    "startTime": 1766139600,
                    "timeZoneOffset": 60
                },
                {
                    "counterId": 30007,
                    "counterValue": 5.0,
                    "dnId": 118748818,
                    "dstOffset": 0,
                    "period": 300,
                    "startTime": 1766139900,
                    "timeZoneOffset": 60
                },
                {
                    "counterId": 30007,
                    "counterValue": 5.0,
                    "dnId": 118748818,
                    "dstOffset": 0,
                    "period": 300,
                    "startTime": 1766140200,
                    "timeZoneOffset": 60
                },
                {
                    "counterId": 30007,
                    "counterValue": 5.0,
                    "dnId": 118748818,
                    "dstOffset": 0,
                    "period": 300,
                    "startTime": 1766140500,
                    "timeZoneOffset": 60
                },
                {
                    "counterId": 30007,
                    "counterValue": 5.0,
                    "dnId": 118748818,
                    "dstOffset": 0,
                    "period": 300,
                    "startTime": 1766140800,
                    "timeZoneOffset": 60
                },
                {
                    "counterId": 30007,
                    "counterValue": 5.0,
                    "dnId": 118748818,
                    "dstOffset": 0,
                    "period": 300,
                    "startTime": 1766141100,
                    "timeZoneOffset": 60
                },
                {
                    "counterId": 30007,
                    "counterValue": 5.0,
                    "dnId": 118748818,
                    "dstOffset": 0,
                    "period": 300,
                    "startTime": 1766141400,
                    "timeZoneOffset": 60
                },
                {
                    "counterId": 30007,
                    "counterValue": 5.0,
                    "dnId": 118748818,
                    "dstOffset": 0,
                    "period": 300,
                    "startTime": 1766141700,
                    "timeZoneOffset": 60
                },
                {
                    "counterId": 30007,
                    "counterValue": 5.0,
                    "dnId": 118748818,
                    "dstOffset": 0,
                    "period": 300,
                    "startTime": 1766142000,
                    "timeZoneOffset": 60
                },
                {
                    "counterId": 30007,
                    "counterValue": 5.0,
                    "dnId": 118748818,
                    "dstOffset": 0,
                    "period": 300,
                    "startTime": 1766142300,
                    "timeZoneOffset": 60
                },
                {
                    "counterId": 30007,
                    "counterValue": 5.0,
                    "dnId": 118748818,
                    "dstOffset": 0,
                    "period": 300,
                    "startTime": 1766142600,
                    "timeZoneOffset": 60
                },
                {
                    "counterId": 30007,
                    "counterValue": 5.0,
                    "dnId": 118748818,
                    "dstOffset": 0,
                    "period": 300,
                    "startTime": 1766142900,
                    "timeZoneOffset": 60
                },
                {
                    "counterId": 30007,
                    "counterValue": 5.0,
                    "dnId": 118748818,
                    "dstOffset": 0,
                    "period": 300,
                    "startTime": 1766143200,
                    "timeZoneOffset": 60
                },
                {
                    "counterId": 30007,
                    "counterValue": 5.0,
                    "dnId": 118748818,
                    "dstOffset": 0,
                    "period": 300,
                    "startTime": 1766143500,
                    "timeZoneOffset": 60
                },
                {
                    "counterId": 30007,
                    "counterValue": 5.0,
                    "dnId": 118748818,
                    "dstOffset": 0,
                    "period": 300,
                    "startTime": 1766143800,
                    "timeZoneOffset": 60
                },
                {
                    "counterId": 30007,
                    "counterValue": 5.0,
                    "dnId": 118748818,
                    "dstOffset": 0,
                    "period": 300,
                    "startTime": 1766144100,
                    "timeZoneOffset": 60
                },
                {
                    "counterId": 30007,
                    "counterValue": 5.0,
                    "dnId": 118748818,
                    "dstOffset": 0,
                    "period": 300,
                    "startTime": 1766144400,
                    "timeZoneOffset": 60
                },
                {
                    "counterId": 30007,
                    "counterValue": 5.0,
                    "dnId": 118748818,
                    "dstOffset": 0,
                    "period": 300,
                    "startTime": 1766144700,
                    "timeZoneOffset": 60
                },
                {
                    "counterId": 30007,
                    "counterValue": 5.0,
                    "dnId": 118748818,
                    "dstOffset": 0,
                    "period": 300,
                    "startTime": 1766145000,
                    "timeZoneOffset": 60
                },
                {
                    "counterId": 30007,
                    "counterValue": 5.0,
                    "dnId": 118748818,
                    "dstOffset": 0,
                    "period": 300,
                    "startTime": 1766145300,
                    "timeZoneOffset": 60
                },
                {
                    "counterId": 30007,
                    "counterValue": 5.0,
                    "dnId": 118748818,
                    "dstOffset": 0,
                    "period": 300,
                    "startTime": 1766145600,
                    "timeZoneOffset": 60
                },
                {
                    "counterId": 30007,
                    "counterValue": 5.0,
                    "dnId": 118748818,
                    "dstOffset": 0,
                    "period": 300,
                    "startTime": 1766145900,
                    "timeZoneOffset": 60
                },
                {
                    "counterId": 30007,
                    "counterValue": 5.0,
                    "dnId": 118748818,
                    "dstOffset": 0,
                    "period": 300,
                    "startTime": 1766146200,
                    "timeZoneOffset": 60
                },
                {
                    "counterId": 30007,
                    "counterValue": 5.0,
                    "dnId": 118748818,
                    "dstOffset": 0,
                    "period": 300,
                    "startTime": 1766146500,
                    "timeZoneOffset": 60
                },
                {
                    "counterId": 30007,
                    "counterValue": 5.0,
                    "dnId": 118748818,
                    "dstOffset": 0,
                    "period": 300,
                    "startTime": 1766146800,
                    "timeZoneOffset": 60
                },
                {
                    "counterId": 30007,
                    "counterValue": 5.0,
                    "dnId": 118748818,
                    "dstOffset": 0,
                    "period": 300,
                    "startTime": 1766147100,
                    "timeZoneOffset": 60
                },
                {
                    "counterId": 30007,
                    "counterValue": 5.0,
                    "dnId": 118748818,
                    "dstOffset": 0,
                    "period": 300,
                    "startTime": 1766147400,
                    "timeZoneOffset": 60
                },
                {
                    "counterId": 30007,
                    "counterValue": 5.0,
                    "dnId": 118748818,
                    "dstOffset": 0,
                    "period": 300,
                    "startTime": 1766147700,
                    "timeZoneOffset": 60
                },
                {
                    "counterId": 30007,
                    "counterValue": 5.0,
                    "dnId": 118748818,
                    "dstOffset": 0,
                    "period": 300,
                    "startTime": 1766148000,
                    "timeZoneOffset": 60
                },
                {
                    "counterId": 30007,
                    "counterValue": 5.0,
                    "dnId": 118748818,
                    "dstOffset": 0,
                    "period": 300,
                    "startTime": 1766148300,
                    "timeZoneOffset": 60
                },
                {
                    "counterId": 30007,
                    "counterValue": 5.0,
                    "dnId": 118748818,
                    "dstOffset": 0,
                    "period": 300,
                    "startTime": 1766148600,
                    "timeZoneOffset": 60
                },
                {
                    "counterId": 30007,
                    "counterValue": 5.0,
                    "dnId": 118748818,
                    "dstOffset": 0,
                    "period": 300,
                    "startTime": 1766148900,
                    "timeZoneOffset": 60
                },
                {
                    "counterId": 30007,
                    "counterValue": 5.0,
                    "dnId": 118748818,
                    "dstOffset": 0,
                    "period": 300,
                    "startTime": 1766149200,
                    "timeZoneOffset": 60
                },
                {
                    "counterId": 30007,
                    "counterValue": 5.0,
                    "dnId": 118748818,
                    "dstOffset": 0,
                    "period": 300,
                    "startTime": 1766149500,
                    "timeZoneOffset": 60
                },
                {
                    "counterId": 30007,
                    "counterValue": 5.0,
                    "dnId": 118748818,
                    "dstOffset": 0,
                    "period": 300,
                    "startTime": 1766149800,
                    "timeZoneOffset": 60
                },
                {
                    "counterId": 30007,
                    "counterValue": 5.0,
                    "dnId": 118748818,
                    "dstOffset": 0,
                    "period": 300,
                    "startTime": 1766150100,
                    "timeZoneOffset": 60
                },
                {
                    "counterId": 30007,
                    "counterValue": 5.0,
                    "dnId": 118748818,
                    "dstOffset": 0,
                    "period": 300,
                    "startTime": 1766150400,
                    "timeZoneOffset": 60
                },
                {
                    "counterId": 30007,
                    "counterValue": 5.0,
                    "dnId": 118748818,
                    "dstOffset": 0,
                    "period": 300,
                    "startTime": 1766150700,
                    "timeZoneOffset": 60
                },
                {
                    "counterId": 30007,
                    "counterValue": 5.0,
                    "dnId": 118748818,
                    "dstOffset": 0,
                    "period": 300,
                    "startTime": 1766151000,
                    "timeZoneOffset": 60
                },
                {
                    "counterId": 30007,
                    "counterValue": 5.0,
                    "dnId": 118748818,
                    "dstOffset": 0,
                    "period": 300,
                    "startTime": 1766151300,
                    "timeZoneOffset": 60
                },
                {
                    "counterId": 30007,
                    "counterValue": 5.0,
                    "dnId": 118748818,
                    "dstOffset": 0,
                    "period": 300,
                    "startTime": 1766151600,
                    "timeZoneOffset": 60
                },
                {
                    "counterId": 30007,
                    "counterValue": 5.0,
                    "dnId": 118748818,
                    "dstOffset": 0,
                    "period": 300,
                    "startTime": 1766151900,
                    "timeZoneOffset": 60
                },
                {
                    "counterId": 30007,
                    "counterValue": 5.0,
                    "dnId": 118748818,
                    "dstOffset": 0,
                    "period": 300,
                    "startTime": 1766152200,
                    "timeZoneOffset": 60
                },
                {
                    "counterId": 30007,
                    "counterValue": 5.0,
                    "dnId": 118748818,
                    "dstOffset": 0,
                    "period": 300,
                    "startTime": 1766152500,
                    "timeZoneOffset": 60
                },
                {
                    "counterId": 30007,
                    "counterValue": 5.0,
                    "dnId": 118748818,
                    "dstOffset": 0,
                    "period": 300,
                    "startTime": 1766152800,
                    "timeZoneOffset": 60
                },
                {
                    "counterId": 30007,
                    "counterValue": 5.0,
                    "dnId": 118748818,
                    "dstOffset": 0,
                    "period": 300,
                    "startTime": 1766153100,
                    "timeZoneOffset": 60
                },
                {
                    "counterId": 30007,
                    "counterValue": 5.0,
                    "dnId": 118748818,
                    "dstOffset": 0,
                    "period": 300,
                    "startTime": 1766153400,
                    "timeZoneOffset": 60
                },
                {
                    "counterId": 30007,
                    "counterValue": 5.0,
                    "dnId": 118748818,
                    "dstOffset": 0,
                    "period": 300,
                    "startTime": 1766153700,
                    "timeZoneOffset": 60
                },
                {
                    "counterId": 30007,
                    "counterValue": 5.0,
                    "dnId": 118748818,
                    "dstOffset": 0,
                    "period": 300,
                    "startTime": 1766154000,
                    "timeZoneOffset": 60
                },
                {
                    "counterId": 30007,
                    "counterValue": 5.0,
                    "dnId": 118748818,
                    "dstOffset": 0,
                    "period": 300,
                    "startTime": 1766154300,
                    "timeZoneOffset": 60
                },
                {
                    "counterId": 30007,
                    "counterValue": 5.0,
                    "dnId": 118748818,
                    "dstOffset": 0,
                    "period": 300,
                    "startTime": 1766154600,
                    "timeZoneOffset": 60
                },
                {
                    "counterId": 30007,
                    "counterValue": 5.0,
                    "dnId": 118748818,
                    "dstOffset": 0,
                    "period": 300,
                    "startTime": 1766154900,
                    "timeZoneOffset": 60
                },
                {
                    "counterId": 30007,
                    "counterValue": 5.0,
                    "dnId": 118748818,
                    "dstOffset": 0,
                    "period": 300,
                    "startTime": 1766155200,
                    "timeZoneOffset": 60
                },
                {
                    "counterId": 30007,
                    "counterValue": 5.0,
                    "dnId": 118748818,
                    "dstOffset": 0,
                    "period": 300,
                    "startTime": 1766155500,
                    "timeZoneOffset": 60
                },
                {
                    "counterId": 30007,
                    "counterValue": 5.0,
                    "dnId": 118748818,
                    "dstOffset": 0,
                    "period": 300,
                    "startTime": 1766155800,
                    "timeZoneOffset": 60
                },
                {
                    "counterId": 30007,
                    "counterValue": 5.0,
                    "dnId": 118748818,
                    "dstOffset": 0,
                    "period": 300,
                    "startTime": 1766156100,
                    "timeZoneOffset": 60
                },
                {
                    "counterId": 30007,
                    "counterValue": 5.0,
                    "dnId": 118748818,
                    "dstOffset": 0,
                    "period": 300,
                    "startTime": 1766156400,
                    "timeZoneOffset": 60
                },
                {
                    "counterId": 30007,
                    "counterValue": 5.0,
                    "dnId": 118748818,
                    "dstOffset": 0,
                    "period": 300,
                    "startTime": 1766156700,
                    "timeZoneOffset": 60
                },
                {
                    "counterId": 30007,
                    "counterValue": 5.0,
                    "dnId": 118748818,
                    "dstOffset": 0,
                    "period": 300,
                    "startTime": 1766157000,
                    "timeZoneOffset": 60
                },
                {
                    "counterId": 30007,
                    "counterValue": 5.0,
                    "dnId": 118748818,
                    "dstOffset": 0,
                    "period": 300,
                    "startTime": 1766157300,
                    "timeZoneOffset": 60
                },
                {
                    "counterId": 30007,
                    "counterValue": 5.0,
                    "dnId": 118748818,
                    "dstOffset": 0,
                    "period": 300,
                    "startTime": 1766157600,
                    "timeZoneOffset": 60
                },
                {
                    "counterId": 30007,
                    "counterValue": 5.0,
                    "dnId": 118748818,
                    "dstOffset": 0,
                    "period": 300,
                    "startTime": 1766157900,
                    "timeZoneOffset": 60
                },
                {
                    "counterId": 30007,
                    "counterValue": 5.0,
                    "dnId": 118748818,
                    "dstOffset": 0,
                    "period": 300,
                    "startTime": 1766158200,
                    "timeZoneOffset": 60
                },
                {
                    "counterId": 30007,
                    "counterValue": 5.0,
                    "dnId": 118748818,
                    "dstOffset": 0,
                    "period": 300,
                    "startTime": 1766158500,
                    "timeZoneOffset": 60
                },
                {
                    "counterId": 30007,
                    "counterValue": 5.0,
                    "dnId": 118748818,
                    "dstOffset": 0,
                    "period": 300,
                    "startTime": 1766158800,
                    "timeZoneOffset": 60
                },
                {
                    "counterId": 30007,
                    "counterValue": 5.0,
                    "dnId": 118748818,
                    "dstOffset": 0,
                    "period": 300,
                    "startTime": 1766159100,
                    "timeZoneOffset": 60
                },
                {
                    "counterId": 30007,
                    "counterValue": 5.0,
                    "dnId": 118748818,
                    "dstOffset": 0,
                    "period": 300,
                    "startTime": 1766159400,
                    "timeZoneOffset": 60
                },
                {
                    "counterId": 30007,
                    "counterValue": 5.0,
                    "dnId": 118748818,
                    "dstOffset": 0,
                    "period": 300,
                    "startTime": 1766159700,
                    "timeZoneOffset": 60
                },
                {
                    "counterId": 30007,
                    "counterValue": 5.0,
                    "dnId": 118748818,
                    "dstOffset": 0,
                    "period": 300,
                    "startTime": 1766160000,
                    "timeZoneOffset": 60
                },
                {
                    "counterId": 30007,
                    "counterValue": 5.0,
                    "dnId": 118748818,
                    "dstOffset": 0,
                    "period": 300,
                    "startTime": 1766160300,
                    "timeZoneOffset": 60
                },
                {
                    "counterId": 30007,
                    "counterValue": 5.0,
                    "dnId": 118748818,
                    "dstOffset": 0,
                    "period": 300,
                    "startTime": 1766160600,
                    "timeZoneOffset": 60
                },
                {
                    "counterId": 30007,
                    "counterValue": 5.0,
                    "dnId": 118748818,
                    "dstOffset": 0,
                    "period": 300,
                    "startTime": 1766160900,
                    "timeZoneOffset": 60
                },
                {
                    "counterId": 30007,
                    "counterValue": 5.0,
                    "dnId": 118748818,
                    "dstOffset": 0,
                    "period": 300,
                    "startTime": 1766161200,
                    "timeZoneOffset": 60
                },
                {
                    "counterId": 30007,
                    "counterValue": 5.0,
                    "dnId": 118748818,
                    "dstOffset": 0,
                    "period": 300,
                    "startTime": 1766161500,
                    "timeZoneOffset": 60
                },
                {
                    "counterId": 30007,
                    "counterValue": 5.0,
                    "dnId": 118748818,
                    "dstOffset": 0,
                    "period": 300,
                    "startTime": 1766161800,
                    "timeZoneOffset": 60
                },
                {
                    "counterId": 30007,
                    "counterValue": 5.0,
                    "dnId": 118748818,
                    "dstOffset": 0,
                    "period": 300,
                    "startTime": 1766162100,
                    "timeZoneOffset": 60
                },
                {
                    "counterId": 30007,
                    "counterValue": 5.0,
                    "dnId": 118748818,
                    "dstOffset": 0,
                    "period": 300,
                    "startTime": 1766162400,
                    "timeZoneOffset": 60
                },
                {
                    "counterId": 30007,
                    "counterValue": 5.0,
                    "dnId": 118748818,
                    "dstOffset": 0,
                    "period": 300,
                    "startTime": 1766162700,
                    "timeZoneOffset": 60
                },
                {
                    "counterId": 30007,
                    "counterValue": 5.0,
                    "dnId": 118748818,
                    "dstOffset": 0,
                    "period": 300,
                    "startTime": 1766163000,
                    "timeZoneOffset": 60
                },
                {
                    "counterId": 30007,
                    "counterValue": 5.0,
                    "dnId": 118748818,
                    "dstOffset": 0,
                    "period": 300,
                    "startTime": 1766163300,
                    "timeZoneOffset": 60
                },
                {
                    "counterId": 30007,
                    "counterValue": 5.0,
                    "dnId": 118748818,
                    "dstOffset": 0,
                    "period": 300,
                    "startTime": 1766163600,
                    "timeZoneOffset": 60
                },
                {
                    "counterId": 30007,
                    "counterValue": 5.0,
                    "dnId": 118748818,
                    "dstOffset": 0,
                    "period": 300,
                    "startTime": 1766163900,
                    "timeZoneOffset": 60
                },
                {
                    "counterId": 30007,
                    "counterValue": 5.0,
                    "dnId": 118748818,
                    "dstOffset": 0,
                    "period": 300,
                    "startTime": 1766164200,
                    "timeZoneOffset": 60
                },
                {
                    "counterId": 30007,
                    "counterValue": 5.0,
                    "dnId": 118748818,
                    "dstOffset": 0,
                    "period": 300,
                    "startTime": 1766164500,
                    "timeZoneOffset": 60
                },
                {
                    "counterId": 30007,
                    "counterValue": 5.0,
                    "dnId": 118748818,
                    "dstOffset": 0,
                    "period": 300,
                    "startTime": 1766164800,
                    "timeZoneOffset": 60
                },
                {
                    "counterId": 30007,
                    "counterValue": 5.0,
                    "dnId": 118748818,
                    "dstOffset": 0,
                    "period": 300,
                    "startTime": 1766165100,
                    "timeZoneOffset": 60
                },
                {
                    "counterId": 30007,
                    "counterValue": 5.0,
                    "dnId": 118748818,
                    "dstOffset": 0,
                    "period": 300,
                    "startTime": 1766165400,
                    "timeZoneOffset": 60
                },
                {
                    "counterId": 30007,
                    "counterValue": 5.0,
                    "dnId": 118748818,
                    "dstOffset": 0,
                    "period": 300,
                    "startTime": 1766165700,
                    "timeZoneOffset": 60
                },
                {
                    "counterId": 30007,
                    "counterValue": 5.0,
                    "dnId": 118748818,
                    "dstOffset": 0,
                    "period": 300,
                    "startTime": 1766166000,
                    "timeZoneOffset": 60
                },
                {
                    "counterId": 30007,
                    "counterValue": 5.0,
                    "dnId": 118748818,
                    "dstOffset": 0,
                    "period": 300,
                    "startTime": 1766166300,
                    "timeZoneOffset": 60
                },
                {
                    "counterId": 30007,
                    "counterValue": 5.0,
                    "dnId": 118748818,
                    "dstOffset": 0,
                    "period": 300,
                    "startTime": 1766166600,
                    "timeZoneOffset": 60
                },
                {
                    "counterId": 30007,
                    "counterValue": 5.0,
                    "dnId": 118748818,
                    "dstOffset": 0,
                    "period": 300,
                    "startTime": 1766166900,
                    "timeZoneOffset": 60
                },
                {
                    "counterId": 30007,
                    "counterValue": 5.0,
                    "dnId": 118748818,
                    "dstOffset": 0,
                    "period": 300,
                    "startTime": 1766167200,
                    "timeZoneOffset": 60
                },
                {
                    "counterId": 30007,
                    "counterValue": 5.0,
                    "dnId": 118748818,
                    "dstOffset": 0,
                    "period": 300,
                    "startTime": 1766167500,
                    "timeZoneOffset": 60
                },
                {
                    "counterId": 30007,
                    "counterValue": 5.0,
                    "dnId": 118748818,
                    "dstOffset": 0,
                    "period": 300,
                    "startTime": 1766167800,
                    "timeZoneOffset": 60
                },
                {
                    "counterId": 30007,
                    "counterValue": 5.0,
                    "dnId": 118748818,
                    "dstOffset": 0,
                    "period": 300,
                    "startTime": 1766168100,
                    "timeZoneOffset": 60
                },
                {
                    "counterId": 30007,
                    "counterValue": 5.0,
                    "dnId": 118748818,
                    "dstOffset": 0,
                    "period": 300,
                    "startTime": 1766168400,
                    "timeZoneOffset": 60
                },
                {
                    "counterId": 30007,
                    "counterValue": 5.0,
                    "dnId": 118748818,
                    "dstOffset": 0,
                    "period": 300,
                    "startTime": 1766168700,
                    "timeZoneOffset": 60
                },
                {
                    "counterId": 30007,
                    "counterValue": 5.0,
                    "dnId": 118748818,
                    "dstOffset": 0,
                    "period": 300,
                    "startTime": 1766169000,
                    "timeZoneOffset": 60
                },
                {
                    "counterId": 30007,
                    "counterValue": 5.0,
                    "dnId": 118748818,
                    "dstOffset": 0,
                    "period": 300,
                    "startTime": 1766169300,
                    "timeZoneOffset": 60
                },
                {
                    "counterId": 30007,
                    "counterValue": 5.0,
                    "dnId": 118748818,
                    "dstOffset": 0,
                    "period": 300,
                    "startTime": 1766169600,
                    "timeZoneOffset": 60
                },
                {
                    "counterId": 30007,
                    "counterValue": 5.0,
                    "dnId": 118748818,
                    "dstOffset": 0,
                    "period": 300,
                    "startTime": 1766169900,
                    "timeZoneOffset": 60
                },
                {
                    "counterId": 30007,
                    "counterValue": 5.0,
                    "dnId": 118748818,
                    "dstOffset": 0,
                    "period": 300,
                    "startTime": 1766170200,
                    "timeZoneOffset": 60
                },
                {
                    "counterId": 30007,
                    "counterValue": 5.0,
                    "dnId": 118748818,
                    "dstOffset": 0,
                    "period": 300,
                    "startTime": 1766170500,
                    "timeZoneOffset": 60
                },
                {
                    "counterId": 30007,
                    "counterValue": 5.0,
                    "dnId": 118748818,
                    "dstOffset": 0,
                    "period": 300,
                    "startTime": 1766170800,
                    "timeZoneOffset": 60
                },
                {
                    "counterId": 30007,
                    "counterValue": 5.0,
                    "dnId": 118748818,
                    "dstOffset": 0,
                    "period": 300,
                    "startTime": 1766171100,
                    "timeZoneOffset": 60
                },
                {
                    "counterId": 30007,
                    "counterValue": 5.0,
                    "dnId": 118748818,
                    "dstOffset": 0,
                    "period": 300,
                    "startTime": 1766171400,
                    "timeZoneOffset": 60
                },
                {
                    "counterId": 30007,
                    "counterValue": 5.0,
                    "dnId": 118748818,
                    "dstOffset": 0,
                    "period": 300,
                    "startTime": 1766171700,
                    "timeZoneOffset": 60
                },
                {
                    "counterId": 30007,
                    "counterValue": 5.0,
                    "dnId": 118748818,
                    "dstOffset": 0,
                    "period": 300,
                    "startTime": 1766172000,
                    "timeZoneOffset": 60
                },
                {
                    "counterId": 30007,
                    "counterValue": 5.0,
                    "dnId": 118748818,
                    "dstOffset": 0,
                    "period": 300,
                    "startTime": 1766172300,
                    "timeZoneOffset": 60
                },
                {
                    "counterId": 30007,
                    "counterValue": 5.0,
                    "dnId": 118748818,
                    "dstOffset": 0,
                    "period": 300,
                    "startTime": 1766172600,
                    "timeZoneOffset": 60
                },
                {
                    "counterId": 30007,
                    "counterValue": 5.0,
                    "dnId": 118748818,
                    "dstOffset": 0,
                    "period": 300,
                    "startTime": 1766172900,
                    "timeZoneOffset": 60
                },
                {
                    "counterId": 30007,
                    "counterValue": 5.0,
                    "dnId": 118748818,
                    "dstOffset": 0,
                    "period": 300,
                    "startTime": 1766173200,
                    "timeZoneOffset": 60
                },
                {
                    "counterId": 30007,
                    "counterValue": 5.0,
                    "dnId": 118748818,
                    "dstOffset": 0,
                    "period": 300,
                    "startTime": 1766173500,
                    "timeZoneOffset": 60
                },
                {
                    "counterId": 30007,
                    "counterValue": 5.0,
                    "dnId": 118748818,
                    "dstOffset": 0,
                    "period": 300,
                    "startTime": 1766173800,
                    "timeZoneOffset": 60
                },
                {
                    "counterId": 30007,
                    "counterValue": 5.0,
                    "dnId": 118748818,
                    "dstOffset": 0,
                    "period": 300,
                    "startTime": 1766174100,
                    "timeZoneOffset": 60
                },
                {
                    "counterId": 30007,
                    "counterValue": 5.0,
                    "dnId": 118748818,
                    "dstOffset": 0,
                    "period": 300,
                    "startTime": 1766174400,
                    "timeZoneOffset": 60
                },
                {
                    "counterId": 30007,
                    "counterValue": 5.0,
                    "dnId": 118748818,
                    "dstOffset": 0,
                    "period": 300,
                    "startTime": 1766174700,
                    "timeZoneOffset": 60
                },
                {
                    "counterId": 30007,
                    "counterValue": 5.0,
                    "dnId": 118748818,
                    "dstOffset": 0,
                    "period": 300,
                    "startTime": 1766175000,
                    "timeZoneOffset": 60
                },
                {
                    "counterId": 30007,
                    "counterValue": 5.0,
                    "dnId": 118748818,
                    "dstOffset": 0,
                    "period": 300,
                    "startTime": 1766175300,
                    "timeZoneOffset": 60
                },
                {
                    "counterId": 30007,
                    "counterValue": 5.0,
                    "dnId": 118748818,
                    "dstOffset": 0,
                    "period": 300,
                    "startTime": 1766175600,
                    "timeZoneOffset": 60
                },
                {
                    "counterId": 30007,
                    "counterValue": 5.0,
                    "dnId": 118748818,
                    "dstOffset": 0,
                    "period": 300,
                    "startTime": 1766175900,
                    "timeZoneOffset": 60
                },
                {
                    "counterId": 30007,
                    "counterValue": 5.0,
                    "dnId": 118748818,
                    "dstOffset": 0,
                    "period": 300,
                    "startTime": 1766176200,
                    "timeZoneOffset": 60
                },
                {
                    "counterId": 30007,
                    "counterValue": 5.0,
                    "dnId": 118748818,
                    "dstOffset": 0,
                    "period": 300,
                    "startTime": 1766176500,
                    "timeZoneOffset": 60
                },
                {
                    "counterId": 30007,
                    "counterValue": 5.0,
                    "dnId": 118748818,
                    "dstOffset": 0,
                    "period": 300,
                    "startTime": 1766176800,
                    "timeZoneOffset": 60
                },
                {
                    "counterId": 30007,
                    "counterValue": 5.0,
                    "dnId": 118748818,
                    "dstOffset": 0,
                    "period": 300,
                    "startTime": 1766177100,
                    "timeZoneOffset": 60
                },
                {
                    "counterId": 30007,
                    "counterValue": 5.0,
                    "dnId": 118748818,
                    "dstOffset": 0,
                    "period": 300,
                    "startTime": 1766177400,
                    "timeZoneOffset": 60
                },
                {
                    "counterId": 30007,
                    "counterValue": 5.0,
                    "dnId": 118748818,
                    "dstOffset": 0,
                    "period": 300,
                    "startTime": 1766177700,
                    "timeZoneOffset": 60
                },
                {
                    "counterId": 30007,
                    "counterValue": 5.0,
                    "dnId": 118748818,
                    "dstOffset": 0,
                    "period": 300,
                    "startTime": 1766178000,
                    "timeZoneOffset": 60
                },
                {
                    "counterId": 30007,
                    "counterValue": 5.0,
                    "dnId": 118748818,
                    "dstOffset": 0,
                    "period": 300,
                    "startTime": 1766178300,
                    "timeZoneOffset": 60
                },
                {
                    "counterId": 30007,
                    "counterValue": 5.0,
                    "dnId": 118748818,
                    "dstOffset": 0,
                    "period": 300,
                    "startTime": 1766178600,
                    "timeZoneOffset": 60
                },
                {
                    "counterId": 30007,
                    "counterValue": 5.0,
                    "dnId": 118748818,
                    "dstOffset": 0,
                    "period": 300,
                    "startTime": 1766178900,
                    "timeZoneOffset": 60
                },
                {
                    "counterId": 30007,
                    "counterValue": 5.0,
                    "dnId": 118748818,
                    "dstOffset": 0,
                    "period": 300,
                    "startTime": 1766179200,
                    "timeZoneOffset": 60
                },
                {
                    "counterId": 30007,
                    "counterValue": 5.0,
                    "dnId": 118748818,
                    "dstOffset": 0,
                    "period": 300,
                    "startTime": 1766179500,
                    "timeZoneOffset": 60
                },
                {
                    "counterId": 30007,
                    "counterValue": 5.0,
                    "dnId": 118748818,
                    "dstOffset": 0,
                    "period": 300,
                    "startTime": 1766179800,
                    "timeZoneOffset": 60
                },
                {
                    "counterId": 30007,
                    "counterValue": 5.0,
                    "dnId": 118748818,
                    "dstOffset": 0,
                    "period": 300,
                    "startTime": 1766180100,
                    "timeZoneOffset": 60
                },
                {
                    "counterId": 30007,
                    "counterValue": 5.0,
                    "dnId": 118748818,
                    "dstOffset": 0,
                    "period": 300,
                    "startTime": 1766180400,
                    "timeZoneOffset": 60
                },
                {
                    "counterId": 30007,
                    "counterValue": 5.0,
                    "dnId": 118748818,
                    "dstOffset": 0,
                    "period": 300,
                    "startTime": 1766180700,
                    "timeZoneOffset": 60
                },
                {
                    "counterId": 30007,
                    "counterValue": 5.0,
                    "dnId": 118748818,
                    "dstOffset": 0,
                    "period": 300,
                    "startTime": 1766181000,
                    "timeZoneOffset": 60
                },
                {
                    "counterId": 30007,
                    "counterValue": 5.0,
                    "dnId": 118748818,
                    "dstOffset": 0,
                    "period": 300,
                    "startTime": 1766181300,
                    "timeZoneOffset": 60
                },
                {
                    "counterId": 30007,
                    "counterValue": 5.0,
                    "dnId": 118748818,
                    "dstOffset": 0,
                    "period": 300,
                    "startTime": 1766181600,
                    "timeZoneOffset": 60
                },
                {
                    "counterId": 30007,
                    "counterValue": 5.0,
                    "dnId": 118748818,
                    "dstOffset": 0,
                    "period": 300,
                    "startTime": 1766181900,
                    "timeZoneOffset": 60
                },
                {
                    "counterId": 30007,
                    "counterValue": 5.0,
                    "dnId": 118748818,
                    "dstOffset": 0,
                    "period": 300,
                    "startTime": 1766182200,
                    "timeZoneOffset": 60
                },
                {
                    "counterId": 30007,
                    "counterValue": 5.0,
                    "dnId": 118748818,
                    "dstOffset": 0,
                    "period": 300,
                    "startTime": 1766182500,
                    "timeZoneOffset": 60
                },
                {
                    "counterId": 30007,
                    "counterValue": 5.0,
                    "dnId": 118748818,
                    "dstOffset": 0,
                    "period": 300,
                    "startTime": 1766182800,
                    "timeZoneOffset": 60
                },
                {
                    "counterId": 30007,
                    "counterValue": 5.0,
                    "dnId": 118748818,
                    "dstOffset": 0,
                    "period": 300,
                    "startTime": 1766183100,
                    "timeZoneOffset": 60
                },
                {
                    "counterId": 30007,
                    "counterValue": 5.0,
                    "dnId": 118748818,
                    "dstOffset": 0,
                    "period": 300,
                    "startTime": 1766183400,
                    "timeZoneOffset": 60
                },
                {
                    "counterId": 30007,
                    "counterValue": 5.0,
                    "dnId": 118748818,
                    "dstOffset": 0,
                    "period": 300,
                    "startTime": 1766183700,
                    "timeZoneOffset": 60
                },
                {
                    "counterId": 30007,
                    "counterValue": 5.0,
                    "dnId": 118748818,
                    "dstOffset": 0,
                    "period": 300,
                    "startTime": 1766184000,
                    "timeZoneOffset": 60
                },
                {
                    "counterId": 30007,
                    "counterValue": 5.0,
                    "dnId": 118748818,
                    "dstOffset": 0,
                    "period": 300,
                    "startTime": 1766184300,
                    "timeZoneOffset": 60
                },
                {
                    "counterId": 30007,
                    "counterValue": 5.0,
                    "dnId": 118748818,
                    "dstOffset": 0,
                    "period": 300,
                    "startTime": 1766184600,
                    "timeZoneOffset": 60
                },
                {
                    "counterId": 30007,
                    "counterValue": 5.0,
                    "dnId": 118748818,
                    "dstOffset": 0,
                    "period": 300,
                    "startTime": 1766184900,
                    "timeZoneOffset": 60
                }
            ],
            "total": 288
        }
    },
    "failCode": 0,
    "params": [],
    "success": true
}